Workbook
Name f_alumbrado: Simulador!$F$7
Name f_parques: Simulador!$F$8
Name grupo_sim: Simulador!$F$9

Sheet Portada
C2: BOGOTÁ DATAJAM 5 · 2026 · LIBRO DE DATOS
C3: El miedo que no baja
C4: Inseguridad percibida frente a delito registrado en Bogotá
C7: 5.538 adultos de la Bienal 2025 · 1.824 encuestas de la EMV 2024 en Bogotá · 19 localidades urbanas · 10 conjuntos de datos oficiales
C9: PREGUNTA ANALÍTICA
C10: ¿Por qué la inseguridad percibida no baja cuando el delito registrado sí, y en qué territorios debe intervenir primero el Distrito?
C11: H1 | D11: La percepción del barrio depende más del entorno inmediato que del delito registrado en la localidad.
C12: H2 | D12: Parte de la distancia entre miedo y registro es subregistro: donde hay más miedo que delito registrado, más delito queda fuera de las cifras.
C13: H3 | D13: A igual victimización, las mujeres restringen más su vida y temen más el acoso sexual.
C15: EQUIPO #16 · THE DATA SQUAD
C16: Rafael Estiven Londoño Camacho
C17: Brandow Brusly León Rodríguez
C18: Samuel Esteban Riveros Cubides
C20: CONTENIDO
B21: 1 | C21: Resumen | D21: Cifras clave y los tres hallazgos
B22: 2 | C22: Panel_localidad | D22: Las 19 localidades urbanas: percepción, entorno, victimización, registro y contexto
B23: 3 | C23: Indice_brecha | D23: Ranking del Índice de Brecha de Seguridad con intervalo bootstrap de 90 %
B24: 4 | C24: Cifra_oculta | D24: Víctimas por delito registrado y validaciones territoriales
B25: 5 | C25: Modelos | D25: Efectos marginales del logit ponderado, robustez y capacidad predictiva (AUC)
B26: 6 | C26: Genero | D26: Mujeres frente a hombres a igual edad, estrato y victimización
B27: 7 | C27: Serie_delitos | D27: Delitos registrados 2018-2026 (enero-agosto) e índice 2018 = 100
B28: 8 | C28: Simulador | D28: Escenarios de alumbrado y parques sin atracos con fórmulas vivas
B29: 9 | C29: Diccionario | D29: Definición, unidad, fuente y año de cada indicador y variable
B30: 10 | C30: Fuentes | D30: Entidades, conjuntos de datos y enlaces oficiales
B31: 11 | C31: Bitacora | D31: Bitácora de limpieza e integración de cada fuente
B32: 12 | C32: Datos_escenarios | D32: Probabilidades del modelo que alimentan el simulador
C34: CÓMO LEER LOS COLORES
C35: Oro: lo que la gente percibe o vive (encuestas de percepción, entorno y victimización).
C36: Azul: lo que registran las autoridades (SCJ, Línea 123).
C37: Morado y verde: mujeres y hombres.
C38: Crema: celdas editables del simulador.
C39: Gris claro: efectos cuyo intervalo de confianza cruza 0 (no significativos).
C41: Reproducible: todas las cifras salen de outputs/ y data/procesados/ del repositorio, y el libro se regenera con «python src/excel.py». El simulador, el Índice de Brecha, la cifra oculta de Bogotá, el ρ de Spearman y los índices 2018 = 100 son fórmulas vivas.
C43: Proyecto académico para el Bogotá DataJam 5. No es un producto oficial de la Alcaldía de Bogotá.

Sheet Resumen
B1: EL MIEDO QUE NO BAJA · BOGOTÁ DATAJAM 5 · THE DATA SQUAD | P1: ← Portada
B2: Resumen
B3: El delito registrado baja; el miedo no. Cifras clave y los tres hallazgos.
B6: CIFRAS CLAVE
B7: REGISTRO · SCJ | F7: PERCEPCIÓN · BIENAL 2025 | J7: PERCEPCIÓN · BIENAL 2025 | N7: CIFRA OCULTA · EMV 2024 + SCJ
B8: =Serie_delitos!$N$8 -> -0.64996669 | F8: 0.74 | J8: =SUMIFS(Datos_escenarios!$I$8:$I$67,Datos_escenarios!$B$8:$B$67,"Total",Datos_escenarios!$C$8:$C$67,0) -> 0.48389448 | N8: =Cifra_oculta!$J$27 -> 5.5852084
B9: en el hurto a personas registrado, enero-agosto 2019 → 2026 (210.160 → 73.563 casos). | F9: de los adultos califica Bogotá como insegura o muy insegura. | J9: dice lo mismo de su propia zona: el resultado que se modela. | N9: víctimas por cada delito de alto impacto registrado (de 10,6 en Bosa a 0,7 en Los Mártires).
B10: Fuente: Serie_delitos | F10: Fuente: resultados.json (Bienal 2025, ponderado) | J10: Fuente: Datos_escenarios (Bienal 2025, ponderado) | N10: Fuente: Cifra_oculta
B12: ENTORNO · MODELO PRINCIPAL | F12: GÉNERO · EMV 2024 | J12: TERRITORIO · VALIDACIÓN | N12: PREDICCIÓN · AUC
B13: =Modelos!$D$18 -> 13.287182 | F13: =Genero!$F$11 -> 18.019705 | J13: =Cifra_oculta!$J$29 -> 0.71578947 | N13: =Modelos!$D$100-Modelos!$D$99 -> 0.002747421
B14: en la probabilidad de sentir insegura la zona si hay atracos en el parque cercano (IC 95 % 6,2 a 17,5). | F14: de temor al acoso sexual por ser mujer, a igual edad, estrato y victimización (IC 95 % 12,9 a 23,4). | J14: entre el Índice de Brecha y la cifra oculta (Spearman, IC 95 % 0,41 a 0,88; p ajustado = 0,004). | N14: de AUC al sumar el delito registrado al perfil (0,609 → 0,611); con el entorno llega a 0,782.
B15: Fuente: Modelos | F15: Fuente: Genero | J15: Fuente: Cifra_oculta | N15: Fuente: Modelos
B17: TRES HALLAZGOS
B18: 1 | C18: La ciudad no ve buena parte de su delito.
C19: Hay unas 5,6 víctimas por cada delito de alto impacto registrado, de 10,6 en Bosa a 0,7 en Los Mártires. El Índice de Brecha crece donde más se subregistra: ρ = 0,72 (IC 95 % 0,41 a 0,88; p ajustado = 0,004), la única relación territorial que sobrevive a la corrección por pruebas múltiples.
B21: 2 | C21: El barrio se siente por lo que pasa en él.
C22: Ver atracos en el parque cercano suma +13,3 pp a la probabilidad de sentir insegura la zona y los conflictos vecinales hasta +14,7 pp. El hurto registrado de la localidad no tiene efecto (p wild = 0,92) y casi no mejora la predicción: AUC 0,609 → 0,611. Con el entorno llega a 0,782.
B24: 3 | C24: Las mujeres pagan el miedo con autonomía.
C25: A igual edad, estrato y victimización, ser mujer suma +18,0 pp de temor al acoso sexual, +6,5 pp de evitar salir de noche y +9,3 pp de sentir inseguro el barrio, aunque ellas reportan menos victimización (20,6 % frente a 28,4 %).
B27: DÓNDE INTERVENIR PRIMERO · TOP 5 DEL ÍNDICE DE BRECHA
B28: Puesto | C28: Localidad | F28: Índice de Brecha | I28: IC 90 % | M28: Top 5 en las réplicas bootstrap
B29: =Indice_brecha!B8 -> 1 | C29: =Indice_brecha!D8 -> Usme | F29: =Indice_brecha!J8 -> 2.667231 | I29: =Indice_brecha!K8 -> 2.2291948 | K29: =Indice_brecha!L8 -> 2.9840343 | M29: =Indice_brecha!N8 -> 1
B30: =Indice_brecha!B9 -> 2 | C30: =Indice_brecha!D9 -> Ciudad Bolívar | F30: =Indice_brecha!J9 -> 2.3382984 | I30: =Indice_brecha!K9 -> 1.9384042 | K30: =Indice_brecha!L9 -> 2.6146998 | M30: =Indice_brecha!N9 -> 1
B31: =Indice_brecha!B10 -> 3 | C31: =Indice_brecha!D10 -> Bosa | F31: =Indice_brecha!J10 -> 1.9661101 | I31: =Indice_brecha!K10 -> 1.4871105 | K31: =Indice_brecha!L10 -> 2.391961 | M31: =Indice_brecha!N10 -> 0.995
B32: =Indice_brecha!B11 -> 4 | C32: =Indice_brecha!D11 -> Kennedy | F32: =Indice_brecha!J11 -> 1.7169763 | I32: =Indice_brecha!K11 -> 1.2899127 | K32: =Indice_brecha!L11 -> 2.0758893 | M32: =Indice_brecha!N11 -> 0.983
B33: =Indice_brecha!B12 -> 5 | C33: =Indice_brecha!D12 -> San Cristóbal | F33: =Indice_brecha!J12 -> 1.5442032 | I33: =Indice_brecha!K12 -> 0.99503714 | K33: =Indice_brecha!L12 -> 2.0202623 | M33: =Indice_brecha!N12 -> 0.909
B35: Bogotá DataJam 5 · equipo #16 The data squad. Cifras de outputs/resultados.json y outputs/tablas/; las celdas con fórmula se recalculan desde las otras hojas.

Sheet Panel_localidad
B1: EL MIEDO QUE NO BAJA · BOGOTÁ DATAJAM 5 · THE DATA SQUAD | Z1: ← Portada
B2: Panel por localidad
B3: Una fila por localidad urbana (19). Percepción y entorno: % ponderado de adultos. Registro: tasas por 100.000 habitantes con población SDP 2025.
B6: Identificación | E6: Percepción · Bienal 2025 | I6: Entorno · Bienal 2025 | M6: Victimización y autoprotección · EMV 2024 | Q6: Registro · SCJ, enero-agosto 2025 | X6: Contexto
B7: Código | C7: Localidad | D7: Población 2025 (hab.) | E7: Zona insegura (%) | F7: Ciudad insegura (%) | G7: Ciudad peor que antes (%) | H7: Miedo en el espacio público (%) | I7: Alumbrado malo (%) | J7: Drogas en el parque (%) | K7: Acoso en el parque (%) | L7: Presenció acoso a mujeres (%) | M7: Víctima de un delito, último año (%) | N7: Barrio inseguro (%) | O7: No sale de noche (%) | P7: Teme acoso sexual (%) | Q7: Delitos de alto impacto (por 100.000 hab.) | R7: Hurtos (por 100.000 hab.) | S7: Homicidios (por 100.000 hab.) | T7: VIF y delitos sexuales (por 100.000 mujeres) | U7: Llamadas 123 por narcóticos (por 100.000 hab.) | V7: Llamadas 123 por riñas (por 100.000 hab.) | W7: Llamadas 123 por maltrato a mujer (por 100.000 hab.) | X7: Área (km²) | Y7: Luminarias por km² (UAESP 2019) | Z7: Espacio público efectivo (m²/hab.)
B8: 1 | C8: Usaquén | D8: 572925 | E8: 0.24820972 | F8: 0.83797041 | G8: 0.33435077 | H8: 0.078982032 | I8: 0.47171693 | J8: 0.4670872 | K8: 0.23330248 | L8: 0.43476447 | M8: 0.18038244 | N8: 0.44848379 | O8: 0.55386421 | P8: 0.57525541 | Q8: 1782.4323 | R8: 1516.9525 | S8: 6.1090021 | T8: 482.34068 | U8: 450.14618 | V8: 2604.1803 | W8: 698.52075 | X8: 65.201414 | Y8: 397.73677 | Z8: 3.743834
B9: 2 | C9: Chapinero | D9: 163693 | E9: 0.50505065 | F9: 0.81019405 | G9: 0.42844845 | H9: 0.096854258 | I9: 0.33686479 | J9: 0.79762303 | K9: 0.17540805 | L9: 0.43646629 | M9: 0.24949577 | N9: 0.46689416 | O9: 0.5318573 | P9: 0.66525474 | Q9: 6466.373 | R9: 5919.6178 | S9: 6.7198964 | T9: 1023.468 | U9: 712.91992 | V9: 4531.6538 | W9: 924.9021 | X9: 38.008915 | Y9: 352.94351 | Z9: 4.211776
B10: 3 | C10: Santa Fe | D10: 113387 | E10: 0.58063905 | F10: 0.64636523 | G10: 0.29046842 | H10: 0.12414296 | I10: 0.56496333 | J10: 0.67707112 | K10: 0.29787772 | L10: 0.36322829 | M10: 0.22754604 | N10: 0.60337605 | O10: 0.58909488 | P10: 0.5872527 | Q10: 6731.8123 | R10: 5557.9564 | S10: 41.45096 | T10: 2248.0172 | U10: 1848.5364 | V10: 6162.0821 | W10: 1561.9074 | X10: 45.170646 | Y10: 203.76065 | Z10: 30.825462
B11: 4 | C11: San Cristóbal | D11: 401414 | E11: 0.55734341 | F11: 0.58168018 | G11: 0.46740111 | H11: 0.085723448 | I11: 0.36926582 | J11: 0.56223503 | K11: 0.27934659 | L11: 0.37472631 | M11: 0.25563728 | N11: 0.57939427 | O11: 0.59937644 | P11: 0.52790451 | Q11: 1413.2541 | R11: 894.33851 | S11: 14.448923 | T11: 974.23216 | U11: 548.56084 | V11: 4037.4775 | W11: 1244.1021 | X11: 49.098549 | Y11: 364.8173 | Z11: 3.383171
B12: 5 | C12: Usme | D12: 403137 | E12: 0.64641785 | F12: 0.57916034 | G12: 0.18314769 | H12: 0.16494703 | I12: 0.53187591 | J12: 0.60011027 | K12: 0.24066739 | L12: 0.42035293 | M12: 0.19499871 | N12: 0.58965258 | O12: 0.5620497 | P12: 0.66893524 | Q12: 1082.7585 | R12: 695.54519 | S12: 12.154677 | T12: 733.11224 | U12: 524.8836 | V12: 4114.7302 | W12: 1291.6205 | X12: 215.06669 | Y12: 75.957835 | Z12: 4.22503
B13: 6 | C13: Tunjuelito | D13: 177370 | E13: 0.3598543 | F13: 0.89551478 | G13: 0.39501861 | H13: 0.12171071 | I13: 0.66263229 | J13: 0.51729491 | K13: 0.31514767 | L13: 0.4080865 | M13: 0.29300927 | N13: 0.65426125 | O13: 0.6612697 | P13: 0.57066432 | Q13: 2131.7021 | R13: 1585.3865 | S13: 8.456898 | T13: 1043.7751 | U13: 578.45182 | V13: 4337.2611 | W13: 1081.3554 | X13: 9.9109397 | Y13: 715.67381 | Z13: 5.397406
B14: 7 | C14: Bosa | D14: 767340 | E14: 0.57061377 | F14: 0.79694464 | G14: 0.36624177 | H14: 0.097470861 | I14: 0.46487767 | J14: 0.58088004 | K14: 0.25797349 | L14: 0.38093346 | M14: 0.26493196 | N14: 0.59521842 | O14: 0.59400067 | P14: 0.65695972 | Q14: 1127.0102 | R14: 778.9246 | S14: 7.4282587 | T14: 658.17966 | U14: 457.03339 | V14: 3573.5137 | W14: 1115.151 | X14: 23.933196 | Y14: 883.37554 | Z14: 1.989258
B15: 8 | C15: Kennedy | D15: 1080598 | E15: 0.58445401 | F15: 0.75346185 | G15: 0.26929811 | H15: 0.11028364 | I15: 0.47786828 | J15: 0.56853077 | K15: 0.13753063 | L15: 0.31142246 | M15: 0.3052644 | N15: 0.60839815 | O15: 0.53330409 | P15: 0.66271382 | Q15: 1475.1092 | R15: 1109.4783 | S15: 9.994466 | T15: 684.4911 | U15: 551.54646 | V15: 3425.048 | W15: 1029.43 | X15: 38.589734 | Y15: 1037.1411 | Z15: 4.030691
B16: 9 | C16: Fontibón | D16: 391475 | E16: 0.27087933 | F16: 0.76407955 | G16: 0.43832994 | H16: 0.066336148 | I16: 0.39448611 | J16: 0.52478815 | K16: 0.16186334 | L16: 0.28575537 | M16: 0.234958 | N16: 0.41054386 | O16: 0.68170454 | P16: 0.58468735 | Q16: 2511.016 | R16: 2011.6227 | S16: 7.1524363 | T16: 930.11357 | U16: 564.78702 | V16: 3106.7118 | W16: 824.82917 | X16: 33.281002 | Y16: 530.00206 | Z16: 3.736148
B17: 10 | C17: Engativá | D17: 827379 | E17: 0.4939223 | F17: 0.72110267 | G17: 0.40656199 | H17: 0.079849894 | I17: 0.34010925 | J17: 0.69942059 | K17: 0.23889807 | L17: 0.30940569 | M17: 0.23574558 | N17: 0.59674447 | O17: 0.55571942 | P17: 0.65990171 | Q17: 2046.825 | R17: 1571.9519 | S17: 3.7467714 | T17: 892.76921 | U17: 840.84803 | V17: 3422.4944 | W17: 919.53023 | X17: 35.880967 | Y17: 1004.7667 | Z17: 7.6986
B18: 11 | C18: Suba | D18: 1246637 | E18: 0.40472664 | F18: 0.84057323 | G18: 0.48310235 | H18: 0.12527843 | I18: 0.20770945 | J18: 0.82414962 | K18: 0.11369968 | L18: 0.41322987 | M18: 0.23744425 | N18: 0.56535055 | O18: 0.71765813 | P18: 0.63282326 | Q18: 1424.5526 | R18: 1125.107 | S18: 4.6525171 | T18: 563.59066 | U18: 609.88082 | V18: 3154.3264 | W18: 889.99444 | X18: 100.56048 | Y18: 428.35914 | Z18: 3.920187
B19: 12 | C19: Barrios Unidos | D19: 139756 | E19: 0.47263052 | F19: 0.6234958 | G19: 0.5928569 | H19: 0.10933866 | I19: 0.25949513 | J19: 0.78898416 | K19: 0.1466462 | L19: 0.32071023 | M19: 0.20787326 | N19: 0.46890859 | O19: 0.59164683 | P19: 0.61494635 | Q19: 4387.647 | R19: 3713.6152 | S19: 10.017459 | T19: 1263.1006 | U19: 1325.1667 | V19: 4823.4065 | W19: 1087.6098 | X19: 11.903448 | Y19: 985.26072 | Z19: 12.228706
... B26: 19 | C26: Ciudad Bolívar | D26: 680206 | E26: 0.6539123 | F26: 0.60831585 | G26: 0.23649468 | H26: 0.10562954 | I26: 0.60960522 | J26: 0.64683759 | K26: 0.38839318 | L26: 0.5199822 | M26: 0.22479444 | N26: 0.59968204 | O26: 0.56712704 | P26: 0.65615343 | Q26: 1444.1213 | R26: 803.43308 | S26: 24.845414 | T26: 1210.8021 | U26: 440.60182 | V26: 3611.406 | W26: 1220.2186 | X26: 130.00259 | Y26: 207.10356 | Z26: 3.821448
B28: Lectura: más intenso = valor más alto entre las 19 localidades (cada columna con su propia escala). Oro: lo que la gente percibe o vive (encuestas). Azul: lo que registran las autoridades. Las tasas de 2025 usan el corte enero-agosto que publica la SCJ, comparable entre años.
B29: Fuentes: Encuesta Bienal de Cultura Ciudadana 2025 (SCRD), Encuesta Mundial de Valores ola 8 2024 (Datos para la Transparencia), SCJ (delito de alto impacto y Línea 123), SDP (población), UAESP (alumbrado 2019), DADEP (espacio público), IDECA (área). Archivo: data/procesados/panel_localidad_2025.csv. Definiciones en la hoja Diccionario.

Sheet Indice_brecha
B1: EL MIEDO QUE NO BAJA · BOGOTÁ DATAJAM 5 · THE DATA SQUAD | O1: ← Portada
B2: Índice de Brecha de Seguridad
B3: Dónde hay más miedo del que explica el delito registrado. IBS = z(% zona insegura) − z(ln delitos de alto impacto por 100.000).
B7: Puesto | C7: Código | D7: Localidad | E7: Zona insegura (%) | F7: Delitos de alto impacto (por 100.000) | G7: ln(delitos) | H7: z percepción | I7: z registro | J7: IBS | K7: IC 90 % inferior | L7: IC 90 % superior | M7: Puesto en IC 90 % | N7: Prob. de top 5 | O7: Lectura | Q7: Auxiliar del gráfico: error + | R7: Auxiliar del gráfico: error −
B8: 1 | C8: 5 | D8: Usme | E8: =INDEX(Panel_localidad!$E$8:$E$26,MATCH(C8,Panel_localidad!$B$8:$B$26,0)) -> 0.64641785 | F8: =INDEX(Panel_localidad!$Q$8:$Q$26,MATCH(C8,Panel_localidad!$B$8:$B$26,0)) -> 1082.7585 | G8: =LN(F8) -> 6.9872672 | H8: =STANDARDIZE(E8,AVERAGE($E$8:$E$26),STDEV($E$8:$E$26)) -> 1.395231 | I8: =STANDARDIZE(G8,AVERAGE($G$8:$G$26),STDEV($G$8:$G$26)) -> -1.2719999 | J8: =H8-I8 -> 2.667231 | K8: 2.2291948 | L8: 2.9840343 | M8: 1 a 2 | N8: 1 | O8: =IF(J8>0,"Más miedo que delito registrado","Menos miedo que delito registrado") -> Más miedo que delito registrado | Q8: =L8-J8 -> 0.31680329 | R8: =J8-K8 -> 0.43803623
B9: 2 | C9: 19 | D9: Ciudad Bolívar | E9: =INDEX(Panel_localidad!$E$8:$E$26,MATCH(C9,Panel_localidad!$B$8:$B$26,0)) -> 0.6539123 | F9: =INDEX(Panel_localidad!$Q$8:$Q$26,MATCH(C9,Panel_localidad!$B$8:$B$26,0)) -> 1444.1213 | G9: =LN(F9) -> 7.2752563 | H9: =STANDARDIZE(E9,AVERAGE($E$8:$E$26),STDEV($E$8:$E$26)) -> 1.4591459 | I9: =STANDARDIZE(G9,AVERAGE($G$8:$G$26),STDEV($G$8:$G$26)) -> -0.87915251 | J9: =H9-I9 -> 2.3382984 | K9: 1.9384042 | L9: 2.6146998 | M9: 1 a 3 | N9: 1 | O9: =IF(J9>0,"Más miedo que delito registrado","Menos miedo que delito registrado") -> Más miedo que delito registrado | Q9: =L9-J9 -> 0.27640144 | R9: =J9-K9 -> 0.39989421
B10: 3 | C10: 7 | D10: Bosa | E10: =INDEX(Panel_localidad!$E$8:$E$26,MATCH(C10,Panel_localidad!$B$8:$B$26,0)) -> 0.57061377 | F10: =INDEX(Panel_localidad!$Q$8:$Q$26,MATCH(C10,Panel_localidad!$B$8:$B$26,0)) -> 1127.0102 | G10: =LN(F10) -> 7.0273236 | H10: =STANDARDIZE(E10,AVERAGE($E$8:$E$26),STDEV($E$8:$E$26)) -> 0.74875125 | I10: =STANDARDIZE(G10,AVERAGE($G$8:$G$26),STDEV($G$8:$G$26)) -> -1.2173589 | J10: =H10-I10 -> 1.9661101 | K10: 1.4871105 | L10: 2.391961 | M10: 2 a 5 | N10: 0.995 | O10: =IF(J10>0,"Más miedo que delito registrado","Menos miedo que delito registrado") -> Más miedo que delito registrado | Q10: =L10-J10 -> 0.42585084 | R10: =J10-K10 -> 0.47899967
B11: 4 | C11: 8 | D11: Kennedy | E11: =INDEX(Panel_localidad!$E$8:$E$26,MATCH(C11,Panel_localidad!$B$8:$B$26,0)) -> 0.58445401 | F11: =INDEX(Panel_localidad!$Q$8:$Q$26,MATCH(C11,Panel_localidad!$B$8:$B$26,0)) -> 1475.1092 | G11: =LN(F11) -> 7.2964873 | H11: =STANDARDIZE(E11,AVERAGE($E$8:$E$26),STDEV($E$8:$E$26)) -> 0.86678497 | I11: =STANDARDIZE(G11,AVERAGE($G$8:$G$26),STDEV($G$8:$G$26)) -> -0.85019131 | J11: =H11-I11 -> 1.7169763 | K11: 1.2899127 | L11: 2.0758893 | M11: 3 a 5 | N11: 0.983 | O11: =IF(J11>0,"Más miedo que delito registrado","Menos miedo que delito registrado") -> Más miedo que delito registrado | Q11: =L11-J11 -> 0.35891298 | R11: =J11-K11 -> 0.42706354
B12: 5 | C12: 4 | D12: San Cristóbal | E12: =INDEX(Panel_localidad!$E$8:$E$26,MATCH(C12,Panel_localidad!$B$8:$B$26,0)) -> 0.55734341 | F12: =INDEX(Panel_localidad!$Q$8:$Q$26,MATCH(C12,Panel_localidad!$B$8:$B$26,0)) -> 1413.2541 | G12: =LN(F12) -> 7.2536502 | H12: =STANDARDIZE(E12,AVERAGE($E$8:$E$26),STDEV($E$8:$E$26)) -> 0.63557768 | I12: =STANDARDIZE(G12,AVERAGE($G$8:$G$26),STDEV($G$8:$G$26)) -> -0.90862552 | J12: =H12-I12 -> 1.5442032 | K12: 0.99503714 | L12: 2.0202623 | M12: 3 a 6 | N12: 0.909 | O12: =IF(J12>0,"Más miedo que delito registrado","Menos miedo que delito registrado") -> Más miedo que delito registrado | Q12: =L12-J12 -> 0.47605913 | R12: =J12-K12 -> 0.54916606
B13: 6 | C13: 18 | D13: Rafael Uribe Uribe | E13: =INDEX(Panel_localidad!$E$8:$E$26,MATCH(C13,Panel_localidad!$B$8:$B$26,0)) -> 0.49708092 | F13: =INDEX(Panel_localidad!$Q$8:$Q$26,MATCH(C13,Panel_localidad!$B$8:$B$26,0)) -> 1542.3005 | G13: =LN(F13) -> 7.3410304 | H13: =STANDARDIZE(E13,AVERAGE($E$8:$E$26),STDEV($E$8:$E$26)) -> 0.12164126 | I13: =STANDARDIZE(G13,AVERAGE($G$8:$G$26),STDEV($G$8:$G$26)) -> -0.78942978 | J13: =H13-I13 -> 0.91107104 | K13: 0.41804018 | L13: 1.3753439 | M13: 5 a 7 | N13: 0.11 | O13: =IF(J13>0,"Más miedo que delito registrado","Menos miedo que delito registrado") -> Más miedo que delito registrado | Q13: =L13-J13 -> 0.46427283 | R13: =J13-K13 -> 0.49303086
B14: 7 | C14: 10 | D14: Engativá | E14: =INDEX(Panel_localidad!$E$8:$E$26,MATCH(C14,Panel_localidad!$B$8:$B$26,0)) -> 0.4939223 | F14: =INDEX(Panel_localidad!$Q$8:$Q$26,MATCH(C14,Panel_localidad!$B$8:$B$26,0)) -> 2046.825 | G14: =LN(F14) -> 7.6240451 | H14: =STANDARDIZE(E14,AVERAGE($E$8:$E$26),STDEV($E$8:$E$26)) -> 0.094703647 | I14: =STANDARDIZE(G14,AVERAGE($G$8:$G$26),STDEV($G$8:$G$26)) -> -0.40336806 | J14: =H14-I14 -> 0.4980717 | K14: 0.17770535 | L14: 0.81816726 | M14: 6 a 8 | N14: 0.002 | O14: =IF(J14>0,"Más miedo que delito registrado","Menos miedo que delito registrado") -> Más miedo que delito registrado | Q14: =L14-J14 -> 0.32009556 | R14: =J14-K14 -> 0.32036635
B15: 8 | C15: 11 | D15: Suba | E15: =INDEX(Panel_localidad!$E$8:$E$26,MATCH(C15,Panel_localidad!$B$8:$B$26,0)) -> 0.40472664 | F15: =INDEX(Panel_localidad!$Q$8:$Q$26,MATCH(C15,Panel_localidad!$B$8:$B$26,0)) -> 1424.5526 | G15: =LN(F15) -> 7.2616131 | H15: =STANDARDIZE(E15,AVERAGE($E$8:$E$26),STDEV($E$8:$E$26)) -> -0.66598352 | I15: =STANDARDIZE(G15,AVERAGE($G$8:$G$26),STDEV($G$8:$G$26)) -> -0.89776335 | J15: =H15-I15 -> 0.23177983 | K15: -0.061453192 | L15: 0.5908302 | M15: 7 a 9 | N15: 0.001 | O15: =IF(J15>0,"Más miedo que delito registrado","Menos miedo que delito registrado") -> Más miedo que delito registrado | Q15: =L15-J15 -> 0.35905037 | R15: =J15-K15 -> 0.29323302
B16: 9 | C16: 15 | D16: Antonio Nariño | E16: =INDEX(Panel_localidad!$E$8:$E$26,MATCH(C16,Panel_localidad!$B$8:$B$26,0)) -> 0.49292851 | F16: =INDEX(Panel_localidad!$Q$8:$Q$26,MATCH(C16,Panel_localidad!$B$8:$B$26,0)) -> 3678.6278 | G16: =LN(F16) -> 8.2102951 | H16: =STANDARDIZE(E16,AVERAGE($E$8:$E$26),STDEV($E$8:$E$26)) -> 0.086228246 | I16: =STANDARDIZE(G16,AVERAGE($G$8:$G$26),STDEV($G$8:$G$26)) -> 0.39633852 | J16: =H16-I16 -> -0.31011028 | K16: -0.783809 | L16: 0.1336726 | M16: 9 a 13 | N16: 0 | O16: =IF(J16>0,"Más miedo que delito registrado","Menos miedo que delito registrado") -> Menos miedo que delito registrado | Q16: =L16-J16 -> 0.44378288 | R16: =J16-K16 -> 0.47369872
B17: 10 | C17: 3 | D17: Santa Fe | E17: =INDEX(Panel_localidad!$E$8:$E$26,MATCH(C17,Panel_localidad!$B$8:$B$26,0)) -> 0.58063905 | F17: =INDEX(Panel_localidad!$Q$8:$Q$26,MATCH(C17,Panel_localidad!$B$8:$B$26,0)) -> 6731.8123 | G17: =LN(F17) -> 8.8145997 | H17: =STANDARDIZE(E17,AVERAGE($E$8:$E$26),STDEV($E$8:$E$26)) -> 0.83424984 | I17: =STANDARDIZE(G17,AVERAGE($G$8:$G$26),STDEV($G$8:$G$26)) -> 1.2206734 | J17: =H17-I17 -> -0.38642358 | K17: -0.98787665 | L17: 0.10114657 | M17: 9 a 14 | N17: 0 | O17: =IF(J17>0,"Más miedo que delito registrado","Menos miedo que delito registrado") -> Menos miedo que delito registrado | Q17: =L17-J17 -> 0.48757015 | R17: =J17-K17 -> 0.60145307
B18: 11 | C18: 16 | D18: Puente Aranda | E18: =INDEX(Panel_localidad!$E$8:$E$26,MATCH(C18,Panel_localidad!$B$8:$B$26,0)) -> 0.45172579 | F18: =INDEX(Panel_localidad!$Q$8:$Q$26,MATCH(C18,Panel_localidad!$B$8:$B$26,0)) -> 3763.443 | G18: =LN(F18) -> 8.2330895 | H18: =STANDARDIZE(E18,AVERAGE($E$8:$E$26),STDEV($E$8:$E$26)) -> -0.26516075 | I18: =STANDARDIZE(G18,AVERAGE($G$8:$G$26),STDEV($G$8:$G$26)) -> 0.4274325 | J18: =H18-I18 -> -0.69259325 | K18: -1.1558846 | L18: -0.17063775 | M18: 9 a 15 | N18: 0 | O18: =IF(J18>0,"Más miedo que delito registrado","Menos miedo que delito registrado") -> Menos miedo que delito registrado | Q18: =L18-J18 -> 0.5219555 | R18: =J18-K18 -> 0.4632914
B19: 12 | C19: 6 | D19: Tunjuelito | E19: =INDEX(Panel_localidad!$E$8:$E$26,MATCH(C19,Panel_localidad!$B$8:$B$26,0)) -> 0.3598543 | F19: =INDEX(Panel_localidad!$Q$8:$Q$26,MATCH(C19,Panel_localidad!$B$8:$B$26,0)) -> 2131.7021 | G19: =LN(F19) -> 7.664676 | H19: =STANDARDIZE(E19,AVERAGE($E$8:$E$26),STDEV($E$8:$E$26)) -> -1.0486681 | I19: =STANDARDIZE(G19,AVERAGE($G$8:$G$26),STDEV($G$8:$G$26)) -> -0.34794315 | J19: =H19-I19 -> -0.70072495 | K19: -1.0474271 | L19: -0.23337524 | M19: 9 a 14 | N19: 0 | O19: =IF(J19>0,"Más miedo que delito registrado","Menos miedo que delito registrado") -> Menos miedo que delito registrado | Q19: =L19-J19 -> 0.46734971 | R19: =J19-K19 -> 0.34670215
... B26: 19 | C26: 14 | D26: Los Mártires | E26: =INDEX(Panel_localidad!$E$8:$E$26,MATCH(C26,Panel_localidad!$B$8:$B$26,0)) -> 0.39738312 | F26: =INDEX(Panel_localidad!$Q$8:$Q$26,MATCH(C26,Panel_localidad!$B$8:$B$26,0)) -> 7609.511 | G26: =LN(F26) -> 8.9371542 | H26: =STANDARDIZE(E26,AVERAGE($E$8:$E$26),STDEV($E$8:$E$26)) -> -0.72861119 | I26: =STANDARDIZE(G26,AVERAGE($G$8:$G$26),STDEV($G$8:$G$26)) -> 1.3878507 | J26: =H26-I26 -> -2.1164618 | K26: -2.6024342 | L26: -1.5458197 | M26: 17 a 19 | N26: 0 | O26: =IF(J26>0,"Más miedo que delito registrado","Menos miedo que delito registrado") -> Menos miedo que delito registrado | Q26: =L26-J26 -> 0.57064211 | R26: =J26-K26 -> 0.48597236
B27: Cómo se lee: IBS positivo (oro) = la localidad siente más inseguridad de la que predice su delito registrado; negativo (azul) = menos. Columnas E a J son fórmulas vivas sobre la hoja Panel_localidad (z con media y desviación estándar de las 19 localidades; ln porque la tasa es muy asimétrica: el centro concentra delito de población flotante). El intervalo de 90 %, el rango de puestos y la probabilidad de top 5 vienen de 1.000 réplicas bootstrap ponderadas dentro de cada localidad (outputs/tablas/ibs.csv). En rojo, las localidades que quedan en el top 5 en al menos el 90 % de las réplicas.
B29: IBS por localidad, con intervalo de 90 %

Sheet Cifra_oculta
B1: EL MIEDO QUE NO BAJA · BOGOTÁ DATAJAM 5 · THE DATA SQUAD | O1: ← Portada
B2: Cifra oculta
B3: Víctimas estimadas (EMV 2024) por cada delito de alto impacto registrado por la SCJ en 2024. Personas frente a hechos: se lee como orden de magnitud.
B7: Código | C7: Localidad | D7: Víctimas, último año (% adultos) | E7: Error estándar | F7: Víctimas estimadas (adultos) | G7: IC 95 % inferior | H7: IC 95 % superior | I7: Delitos registrados 2024 (anualizados) | J7: Víctimas por delito registrado | K7: IC 95 % inferior | L7: IC 95 % superior | M7: IBS | N7: Puesto en cifra oculta | O7: Puesto en IBS | Q7: Auxiliar del gráfico: error + | R7: Auxiliar del gráfico: error −
B8: 7 | C8: Bosa | D8: 0.26493196 | E8: 4.5782724 | F8: 150816.23 | G8: 99733.811 | H8: 201898.64 | I8: 14161.5 | J8: =F8/I8 -> 10.649735 | K8: =G8/I8 -> 7.0426022 | L8: =H8/I8 -> 14.256868 | M8: =INDEX(Indice_brecha!$J$8:$J$26,MATCH(B8,Indice_brecha!$C$8:$C$26,0)) -> 1.9661101 | N8: =RANK(J8,$J$8:$J$26,0) -> 1 | O8: =RANK(M8,$M$8:$M$26,0) -> 3 | Q8: =L8-J8 -> 3.6071331 | R8: =J8-K8 -> 3.6071331
B9: 8 | C9: Kennedy | D9: 0.3052644 | E9: 4.7537496 | F9: 257172.74 | G9: 178677.9 | H9: 335667.59 | I9: 28269 | J9: =F9/I9 -> 9.0973414 | K9: =G9/I9 -> 6.3206303 | L9: =H9/I9 -> 11.874053 | M9: =INDEX(Indice_brecha!$J$8:$J$26,MATCH(B9,Indice_brecha!$C$8:$C$26,0)) -> 1.7169763 | N9: =RANK(J9,$J$8:$J$26,0) -> 2 | O9: =RANK(M9,$M$8:$M$26,0) -> 4 | Q9: =L9-J9 -> 2.7767111 | R9: =J9-K9 -> 2.7767111
B10: 4 | C10: San Cristóbal | D10: 0.25563728 | E10: 4.5119474 | F10: 78317.038 | G10: 51224.346 | H10: 105409.73 | I10: 8746.5 | J10: =F10/I10 -> 8.9541003 | K10: =G10/I10 -> 5.8565536 | L10: =H10/I10 -> 12.051647 | M10: =INDEX(Indice_brecha!$J$8:$J$26,MATCH(B10,Indice_brecha!$C$8:$C$26,0)) -> 1.5442032 | N10: =RANK(J10,$J$8:$J$26,0) -> 3 | O10: =RANK(M10,$M$8:$M$26,0) -> 5 | Q10: =L10-J10 -> 3.0975467 | R10: =J10-K10 -> 3.0975467
B11: 11 | C11: Suba | D11: 0.23744425 | E11: 4.5206325 | F11: 236123.35 | G11: 148011.86 | H11: 324234.84 | I11: 28713 | J11: =F11/I11 -> 8.2235695 | K11: =G11/I11 -> 5.1548727 | L11: =H11/I11 -> 11.292266 | M11: =INDEX(Indice_brecha!$J$8:$J$26,MATCH(B11,Indice_brecha!$C$8:$C$26,0)) -> 0.23177983 | N11: =RANK(J11,$J$8:$J$26,0) -> 4 | O11: =RANK(M11,$M$8:$M$26,0) -> 8 | Q11: =L11-J11 -> 3.0686968 | R11: =J11-K11 -> 3.0686968
B12: 6 | C12: Tunjuelito | D12: 0.29300927 | E12: 4.6930107 | F12: 40897.648 | G12: 28058.843 | H12: 53736.452 | I12: 5086.5 | J12: =F12/I12 -> 8.0404301 | K12: =G12/I12 -> 5.516336 | L12: =H12/I12 -> 10.564524 | M12: =INDEX(Indice_brecha!$J$8:$J$26,MATCH(B12,Indice_brecha!$C$8:$C$26,0)) -> -0.70072495 | N12: =RANK(J12,$J$8:$J$26,0) -> 5 | O12: =RANK(M12,$M$8:$M$26,0) -> 12 | Q12: =L12-J12 -> 2.5240941 | R12: =J12-K12 -> 2.5240941
B13: 5 | C13: Usme | D13: 0.19499871 | E13: 4.2069505 | F13: 57411.911 | G13: 33134.983 | H13: 81688.839 | I13: 7578 | J13: =F13/I13 -> 7.5761297 | K13: =G13/I13 -> 4.3725235 | L13: =H13/I13 -> 10.779736 | M13: =INDEX(Indice_brecha!$J$8:$J$26,MATCH(B13,Indice_brecha!$C$8:$C$26,0)) -> 2.667231 | N13: =RANK(J13,$J$8:$J$26,0) -> 6 | O13: =RANK(M13,$M$8:$M$26,0) -> 1 | Q13: =L13-J13 -> 3.2036062 | R13: =J13-K13 -> 3.2036062
B14: 18 | C14: Rafael Uribe Uribe | D14: 0.22563914 | E14: 4.3551829 | F14: 66499.915 | G14: 41342.32 | H14: 91657.511 | I14: 9136.5 | J14: =F14/I14 -> 7.278489 | K14: =G14/I14 -> 4.5249625 | L14: =H14/I14 -> 10.032016 | M14: =INDEX(Indice_brecha!$J$8:$J$26,MATCH(B14,Indice_brecha!$C$8:$C$26,0)) -> 0.91107104 | N14: =RANK(J14,$J$8:$J$26,0) -> 7 | O14: =RANK(M14,$M$8:$M$26,0) -> 6 | Q14: =L14-J14 -> 2.7535266 | R14: =J14-K14 -> 2.7535266
B15: 19 | C15: Ciudad Bolívar | D15: 0.22479444 | E15: 4.4211724 | F15: 111394.86 | G15: 68453.767 | H15: 154335.96 | I15: 16015.5 | J15: =F15/I15 -> 6.9554408 | K15: =G15/I15 -> 4.2742198 | L15: =H15/I15 -> 9.6366617 | M15: =INDEX(Indice_brecha!$J$8:$J$26,MATCH(B15,Indice_brecha!$C$8:$C$26,0)) -> 2.3382984 | N15: =RANK(J15,$J$8:$J$26,0) -> 8 | O15: =RANK(M15,$M$8:$M$26,0) -> 2 | Q15: =L15-J15 -> 2.681221 | R15: =J15-K15 -> 2.681221
B16: 10 | C16: Engativá | D16: 0.23574558 | E16: 4.3938318 | F16: 158545.03 | G16: 100627.7 | H16: 216462.37 | I16: 25215 | J16: =F16/I16 -> 6.2877269 | K16: =G16/I16 -> 3.9907871 | L16: =H16/I16 -> 8.5846667 | M16: =INDEX(Indice_brecha!$J$8:$J$26,MATCH(B16,Indice_brecha!$C$8:$C$26,0)) -> 0.4980717 | N16: =RANK(J16,$J$8:$J$26,0) -> 9 | O16: =RANK(M16,$M$8:$M$26,0) -> 7 | Q16: =L16-J16 -> 2.2969398 | R16: =J16-K16 -> 2.2969398
B17: 1 | C17: Usaquén | D17: 0.18038244 | E17: 4.2379256 | F17: 85439.946 | G17: 46096.164 | H17: 124783.73 | I17: 16792.5 | J17: =F17/I17 -> 5.0879825 | K17: =G17/I17 -> 2.7450447 | L17: =H17/I17 -> 7.4309203 | M17: =INDEX(Indice_brecha!$J$8:$J$26,MATCH(B17,Indice_brecha!$C$8:$C$26,0)) -> -1.4087676 | N17: =RANK(J17,$J$8:$J$26,0) -> 10 | O17: =RANK(M17,$M$8:$M$26,0) -> 16 | Q17: =L17-J17 -> 2.3429378 | R17: =J17-K17 -> 2.3429378
B18: 16 | C18: Puente Aranda | D18: 0.2538965 | E18: 4.5284388 | F18: 52691.647 | G18: 34271.647 | H18: 71111.648 | I18: 10647 | J18: =F18/I18 -> 4.9489666 | K18: =G18/I18 -> 3.2189017 | L18: =H18/I18 -> 6.6790315 | M18: =INDEX(Indice_brecha!$J$8:$J$26,MATCH(B18,Indice_brecha!$C$8:$C$26,0)) -> -0.69259325 | N18: =RANK(J18,$J$8:$J$26,0) -> 11 | O18: =RANK(M18,$M$8:$M$26,0) -> 11 | Q18: =L18-J18 -> 1.7300649 | R18: =J18-K18 -> 1.7300649
B19: 9 | C19: Fontibón | D19: 0.234958 | E19: 4.4557733 | F19: 74742.253 | G19: 46960.79 | H19: 102523.72 | I19: 15823.5 | J19: =F19/I19 -> 4.7234969 | K19: =G19/I19 -> 2.9677878 | L19: =H19/I19 -> 6.479206 | M19: =INDEX(Indice_brecha!$J$8:$J$26,MATCH(B19,Indice_brecha!$C$8:$C$26,0)) -> -1.6829249 | N19: =RANK(J19,$J$8:$J$26,0) -> 12 | O19: =RANK(M19,$M$8:$M$26,0) -> 17 | Q19: =L19-J19 -> 1.7557091 | R19: =J19-K19 -> 1.7557091
... B26: 14 | C26: Los Mártires | D26: 0.27302391 | E26: 4.6382907 | F26: 18499.281 | G26: 12339.459 | H26: 24659.104 | I26: 26367 | J26: =F26/I26 -> 0.70160736 | K26: =G26/I26 -> 0.46798873 | L26: =H26/I26 -> 0.935226 | M26: =INDEX(Indice_brecha!$J$8:$J$26,MATCH(B26,Indice_brecha!$C$8:$C$26,0)) -> -2.1164618 | N26: =RANK(J26,$J$8:$J$26,0) -> 19 | O26: =RANK(M26,$M$8:$M$26,0) -> 19 | Q26: =L26-J26 -> 0.23361864 | R26: =J26-K26 -> 0.23361864
C27: Bogotá (19 localidades) | F27: =SUM(F8:F26) -> 1534832 | I27: =SUM(I8:I26) -> 274803 | J27: =F27/I27 -> 5.5852084
B29: ρ de Spearman entre IBS y cifra oculta (fórmula: correlación de los puestos de las columnas N y O) | J29: =CORREL(N8:N26,O8:O26) -> 0.71578947
B30: Víctimas estimadas = % de víctimas (EMV 2024, 96 encuestas por localidad) × adultos de la localidad (SDP 2024); IC 95 % con el error estándar de la encuesta. Delitos registrados = los 11 delitos de alto impacto de la SCJ en enero-agosto de 2024 llevados a 12 meses (× 12/8). La razón se recalcula con fórmulas (J = F / I). Fuente: outputs/tablas/cifra_oculta.csv.
B32: Víctimas por delito registrado, con IC 95 % | J32: Índice de Brecha frente a cifra oculta
J52: Eje horizontal: IBS. Eje vertical: víctimas por delito registrado.
B54: Validaciones territoriales (Spearman, n = 19, corrección de Benjamini-Hochberg)
B55: Prueba | H55: ρ | I55: IC 95 % inferior | J55: IC 95 % superior | K55: p | L55: p ajustado (BH) | M55: n | N55: ¿Sobrevive a BH?
B56: Drogas en el parque (Bienal) vs incidentes por narcóticos 123 | H56: -0.084210526 | I56: -0.56915848 | J56: 0.40160284 | K56: 0.73178269 | L56: 0.85374648 | M56: 19 | N56: =IF(L56<0.05,"Sí","No") -> No
B57: Zona insegura (Bienal) vs riñas 123 | H57: 0.2245614 | I57: -0.33044635 | J57: 0.66400746 | K57: 0.35534599 | L57: 0.62185548 | M57: 19 | N57: =IF(L57<0.05,"Sí","No") -> No
B58: Alumbrado malo (Bienal) vs luminarias por km² (UAESP 2019) | H58: -0.11052632 | I58: -0.59255381 | J58: 0.42937778 | K58: 0.65238569 | L58: 0.85374648 | M58: 19 | N58: =IF(L58<0.05,"Sí","No") -> No
B59: Víctimas (EMV) vs delitos registrados (SCJ) | H59: 0.026315789 | I59: -0.49203464 | J59: 0.50449979 | K59: 0.9148379 | L59: 0.9148379 | M59: 19 | N59: =IF(L59<0.05,"Sí","No") -> No
B60: Zona insegura (Bienal) vs delitos registrados (SCJ) | H60: -0.24912281 | I60: -0.69181369 | J60: 0.30042431 | K60: 0.30370909 | L60: 0.62185548 | M60: 19 | N60: =IF(L60<0.05,"Sí","No") -> No
B61: Barrio inseguro (EMV) vs zona insegura (Bienal) | H61: 0.34561404 | I61: -0.2053273 | J61: 0.76481254 | K61: 0.14724537 | L61: 0.51535879 | M61: 19 | N61: =IF(L61<0.05,"Sí","No") -> No
B62: Índice de Brecha vs cifra oculta (víctimas por delito registrado) | H62: 0.71578947 | I62: 0.41215357 | J62: 0.8762464 | K62: 0.00056846911 | L62: 0.0039792838 | M62: 19 | N62: =IF(L62<0.05,"Sí","No") -> Sí
B63: Solo la relación entre el Índice de Brecha y la cifra oculta sobrevive a la corrección por pruebas múltiples. Fuente: outputs/tablas/validaciones.csv (IC por bootstrap de 2.000 réplicas).

Sheet Modelos
B1: EL MIEDO QUE NO BAJA · BOGOTÁ DATAJAM 5 · THE DATA SQUAD | Q1: ← Portada
B2: Modelos
B3: Qué explica sentir insegura la zona. Efectos marginales promedio en puntos porcentuales (pp) con IC 95 %.
B6: Nota metodológica. Logit ponderado con el factor de expansión de la Bienal 2025 (las estimaciones representan a 6.308.418 adultos urbanos; n = 5.538). Efecto marginal promedio (AME): cambio en la probabilidad, en pp, al pasar la variable de 0 a 1 (o por unidad indicada). IC 95 % por bootstrap de conglomerados que remuestrea las 19 localidades: con tan pocos conglomerados los errores analíticos agrupados son optimistas. En gris, los efectos cuyo IC cruza 0. El modelo principal usa solo hechos del entorno (no calificaciones) para evitar el sesgo de método común.
B8: 1. Modelo principal: hechos del entorno | J8: Efecto marginal e IC 95 % (oro: IC excluye 0)
B9: Resultado: siente insegura o muy insegura su zona (Bienal 2025). Variables: perfil, delito registrado de la localidad y hechos del entorno.
B10: Variable | C10: Bloque | D10: Efecto marginal (pp) | E10: IC 95 % inferior | F10: IC 95 % superior | G10: p | H10: ¿IC excluye 0? | S10: Auxiliar del gráfico: error + | T10: Auxiliar del gráfico: error −
B11: Ser mujer | C11: Perfil | D11: -1.0746396 | E11: -4.6382854 | F11: 3.349805 | G11: 0.61062391 | H11: =IF(OR(E11>0,F11<0),"Sí","No") -> No | S11: =F11-D11 -> 4.4244446 | T11: =D11-E11 -> 3.5636458
B12: Edad (por año) | C12: Perfil | D12: 0.026058981 | E12: -0.15880359 | F12: 0.18297576 | G12: 0.80225004 | H12: =IF(OR(E12>0,F12<0),"Sí","No") -> No | S12: =F12-D12 -> 0.15691678 | T12: =D12-E12 -> 0.18486257
B13: Estrato (por nivel) | C13: Perfil | D13: -8.168844 | E13: -10.491071 | F13: -3.4132815 | G13: 3.4457034e-08 | H13: =IF(OR(E13>0,F13<0),"Sí","No") -> Sí | S13: =F13-D13 -> 4.7555625 | T13: =D13-E13 -> 2.3222269
B14: Vive en arriendo | C14: Perfil | D14: 1.7524959 | E14: -3.0956166 | F14: 7.0167216 | G14: 0.53773522 | H14: =IF(OR(E14>0,F14<0),"Sí","No") -> No | S14: =F14-D14 -> 5.2642257 | T14: =D14-E14 -> 4.8481125
B15: Hurtos en la localidad (+1.000 por 100 mil) | C15: Delito registrado | D15: -0.10480582 | E15: -5.6097106 | F15: 1.7398451 | G15: 0.92692911 | H15: =IF(OR(E15>0,F15<0),"Sí","No") -> No | S15: =F15-D15 -> 1.844651 | T15: =D15-E15 -> 5.5049048
B16: Homicidios en la localidad (+1 por 100 mil) | C16: Delito registrado | D16: 0.4696428 | E16: 0.015397563 | F16: 1.3135888 | G16: 0.006421752 | H16: =IF(OR(E16>0,F16<0),"Sí","No") -> Sí | S16: =F16-D16 -> 0.84394604 | T16: =D16-E16 -> 0.45424524
B17: Llamadas 123 por narcóticos (+100 por 100 mil) | C17: Delito registrado | D17: -0.3531497 | E17: -1.9576225 | F17: 2.0297435 | G17: 0.54917126 | H17: =IF(OR(E17>0,F17<0),"Sí","No") -> No | S17: =F17-D17 -> 2.3828932 | T17: =D17-E17 -> 1.6044728
B18: Atracos en el parque más cercano | C18: Hechos del entorno | D18: 13.287182 | E18: 6.2177022 | F18: 17.500551 | G18: 4.2278527e-06 | H18: =IF(OR(E18>0,F18<0),"Sí","No") -> Sí | S18: =F18-D18 -> 4.2133691 | T18: =D18-E18 -> 7.0694799
B19: Venta o consumo de drogas en el parque | C19: Hechos del entorno | D19: -2.8708365 | E19: -7.4040351 | F19: 3.9744723 | G19: 0.25356339 | H19: =IF(OR(E19>0,F19<0),"Sí","No") -> No | S19: =F19-D19 -> 6.8453087 | T19: =D19-E19 -> 4.5331987
B20: No tiene parque cerca | C20: Hechos del entorno | D20: -6.8802082 | E20: -12.731291 | F20: -2.6420744 | G20: 0.0082378474 | H20: =IF(OR(E20>0,F20<0),"Sí","No") -> Sí | S20: =F20-D20 -> 4.2381338 | T20: =D20-E20 -> 5.8510827
B21: Presenció acoso a mujeres | C21: Hechos del entorno | D21: 2.7069786 | E21: -2.126917 | F21: 9.2193881 | G21: 0.37312464 | H21: =IF(OR(E21>0,F21<0),"Sí","No") -> No | S21: =F21-D21 -> 6.5124094 | T21: =D21-E21 -> 4.8338956
B22: Conflictos vecinales (de ninguno a todos) | C22: Hechos del entorno | D22: 14.689478 | E22: 3.8603658 | F22: 23.794378 | G22: 0.0079566072 | H22: =IF(OR(E22>0,F22<0),"Sí","No") -> Sí | S22: =F22-D22 -> 9.1049009 | T22: =D22-E22 -> 10.829112
B24: 2. Con calificaciones del entorno
B25: Agrega alumbrado malo y ventas informales. Comparten batería de preguntas con la seguridad de la zona (sesgo de método común): se reportan aparte, no como causa.
B26: Variable | C26: Bloque | D26: Efecto marginal (pp) | E26: IC 95 % inferior | F26: IC 95 % superior | G26: p | H26: ¿IC excluye 0?
B27: Ser mujer | C27: Perfil | D27: -1.3881277 | E27: -4.6714704 | F27: 2.246066 | G27: 0.44357556 | H27: =IF(OR(E27>0,F27<0),"Sí","No") -> No
B28: Edad (por año) | C28: Perfil | D28: 0.055064171 | E28: -0.083864469 | F28: 0.16054706 | G28: 0.48205814 | H28: =IF(OR(E28>0,F28<0),"Sí","No") -> No
B29: Estrato (por nivel) | C29: Perfil | D29: -5.7791129 | E29: -7.0878767 | F29: -2.3531551 | G29: 1.1249333e-09 | H29: =IF(OR(E29>0,F29<0),"Sí","No") -> Sí
B30: Vive en arriendo | C30: Perfil | D30: 1.3066267 | E30: -1.9591467 | F30: 5.1289541 | G30: 0.48735966 | H30: =IF(OR(E30>0,F30<0),"Sí","No") -> No
B31: Hurtos en la localidad (+1.000 por 100 mil) | C31: Delito registrado | D31: -0.98149248 | E31: -6.9726833 | F31: 1.3811971 | G31: 0.46313391 | H31: =IF(OR(E31>0,F31<0),"Sí","No") -> No
B32: Homicidios en la localidad (+1 por 100 mil) | C32: Delito registrado | D32: 0.31605952 | E32: -0.10665208 | F32: 1.439944 | G32: 0.11706926 | H32: =IF(OR(E32>0,F32<0),"Sí","No") -> No
B33: Llamadas 123 por narcóticos (+100 por 100 mil) | C33: Delito registrado | D33: 0.50548784 | E33: -1.3735298 | F33: 3.0331303 | G33: 0.4850101 | H33: =IF(OR(E33>0,F33<0),"Sí","No") -> No
B34: Atracos en el parque más cercano | C34: Hechos del entorno | D34: 10.150759 | E34: 4.051906 | F34: 14.317114 | G34: 0.00029176027 | H34: =IF(OR(E34>0,F34<0),"Sí","No") -> Sí
B35: Venta o consumo de drogas en el parque | C35: Hechos del entorno | D35: 0.47073111 | E35: -1.8542461 | F35: 3.9548869 | G35: 0.73611055 | H35: =IF(OR(E35>0,F35<0),"Sí","No") -> No
B36: No tiene parque cerca | C36: Hechos del entorno | D36: -13.052133 | E36: -17.583372 | F36: -8.850851 | G36: 7.6864093e-10 | H36: =IF(OR(E36>0,F36<0),"Sí","No") -> Sí
B37: Presenció acoso a mujeres | C37: Hechos del entorno | D37: -0.63741774 | E37: -3.9664502 | F37: 3.0609851 | G37: 0.72945721 | H37: =IF(OR(E37>0,F37<0),"Sí","No") -> No
B38: Conflictos vecinales (de ninguno a todos) | C38: Hechos del entorno | D38: 11.711745 | E38: 5.1667908 | F38: 18.766429 | G38: 0.00053015567 | H38: =IF(OR(E38>0,F38<0),"Sí","No") -> Sí
... B40: Ventas informales: situación mala | C40: Calificación del entorno | D40: 34.958312 | E40: 30.37667 | F40: 39.930056 | G40: 2.4087862e-44 | H40: =IF(OR(E40>0,F40<0),"Sí","No") -> Sí
B42: 3. Resultado alterno: la ciudad es insegura
B43: Mismas variables del modelo principal. La percepción de la ciudad casi no depende del entorno inmediato.
B44: Variable | C44: Bloque | D44: Efecto marginal (pp) | E44: IC 95 % inferior | F44: IC 95 % superior | G44: p | H44: ¿IC excluye 0?
B45: Ser mujer | C45: Perfil | D45: 3.4091791 | E45: 0.18817208 | F45: 5.4307575 | G45: 0.038648877 | H45: =IF(OR(E45>0,F45<0),"Sí","No") -> Sí
B46: Edad (por año) | C46: Perfil | D46: 0.10492914 | E46: 0.00095136488 | F46: 0.19804353 | G46: 0.050688673 | H46: =IF(OR(E46>0,F46<0),"Sí","No") -> Sí
B47: Estrato (por nivel) | C47: Perfil | D47: 1.4557322 | E47: -2.1792545 | F47: 4.3794426 | G47: 0.35297403 | H47: =IF(OR(E47>0,F47<0),"Sí","No") -> No
B48: Vive en arriendo | C48: Perfil | D48: 4.4223472 | E48: -1.1501597 | F48: 9.4987826 | G48: 0.12422839 | H48: =IF(OR(E48>0,F48<0),"Sí","No") -> No
B49: Hurtos en la localidad (+1.000 por 100 mil) | C49: Delito registrado | D49: 0.38608283 | E49: -1.9845853 | F49: 4.0875278 | G49: 0.78677845 | H49: =IF(OR(E49>0,F49<0),"Sí","No") -> No
B50: Homicidios en la localidad (+1 por 100 mil) | C50: Delito registrado | D50: -0.54275026 | E50: -1.2055289 | F50: 0.31451529 | G50: 0.013534888 | H50: =IF(OR(E50>0,F50<0),"Sí","No") -> No
B51: Llamadas 123 por narcóticos (+100 por 100 mil) | C51: Delito registrado | D51: -0.34876224 | E51: -2.9415372 | F51: 1.0347568 | G51: 0.62399457 | H51: =IF(OR(E51>0,F51<0),"Sí","No") -> No
B52: Atracos en el parque más cercano | C52: Hechos del entorno | D52: 0.37126763 | E52: -3.6973814 | F52: 4.2382122 | G52: 0.86475352 | H52: =IF(OR(E52>0,F52<0),"Sí","No") -> No
B53: Venta o consumo de drogas en el parque | C53: Hechos del entorno | D53: 3.8506206 | E53: -2.0083586 | F53: 9.057475 | G53: 0.26064407 | H53: =IF(OR(E53>0,F53<0),"Sí","No") -> No
B54: No tiene parque cerca | C54: Hechos del entorno | D54: 2.9020601 | E54: -2.2440064 | F54: 9.5731148 | G54: 0.35546382 | H54: =IF(OR(E54>0,F54<0),"Sí","No") -> No
B55: Presenció acoso a mujeres | C55: Hechos del entorno | D55: -3.0784038 | E55: -8.0296537 | F55: 2.6347304 | G55: 0.30723936 | H55: =IF(OR(E55>0,F55<0),"Sí","No") -> No
B56: Conflictos vecinales (de ninguno a todos) | C56: Hechos del entorno | D56: 0.65686614 | E56: -7.2495215 | F56: 11.115467 | G56: 0.90283869 | H56: =IF(OR(E56>0,F56<0),"Sí","No") -> No
B58: 4. Resultado alterno: miedo en el espacio público
B59: Mismas variables del modelo principal.
B60: Variable | C60: Bloque | D60: Efecto marginal (pp) | E60: IC 95 % inferior | F60: IC 95 % superior | G60: p | H60: ¿IC excluye 0?
B61: Ser mujer | C61: Perfil | D61: 3.8632815 | E61: 1.9410249 | F61: 5.7151181 | G61: 0.00047524404 | H61: =IF(OR(E61>0,F61<0),"Sí","No") -> Sí
B62: Edad (por año) | C62: Perfil | D62: 0.038024159 | E62: -0.034131578 | F62: 0.11072528 | G62: 0.36543025 | H62: =IF(OR(E62>0,F62<0),"Sí","No") -> No
B63: Estrato (por nivel) | C63: Perfil | D63: -0.69003162 | E63: -2.567921 | F63: 1.3064836 | G63: 0.52639973 | H63: =IF(OR(E63>0,F63<0),"Sí","No") -> No
B64: Vive en arriendo | C64: Perfil | D64: -2.2288541 | E64: -5.1940987 | F64: 1.4711421 | G64: 0.21898191 | H64: =IF(OR(E64>0,F64<0),"Sí","No") -> No
B65: Hurtos en la localidad (+1.000 por 100 mil) | C65: Delito registrado | D65: -0.86775179 | E65: -2.9619856 | F65: 0.3820072 | G65: 0.21244225 | H65: =IF(OR(E65>0,F65<0),"Sí","No") -> No
B66: Homicidios en la localidad (+1 por 100 mil) | C66: Delito registrado | D66: -0.0037188775 | E66: -0.1926286 | F66: 0.30315713 | G66: 0.96954883 | H66: =IF(OR(E66>0,F66<0),"Sí","No") -> No
B67: Llamadas 123 por narcóticos (+100 por 100 mil) | C67: Delito registrado | D67: 0.50503356 | E67: -0.34791984 | F67: 1.5422337 | G67: 0.21518413 | H67: =IF(OR(E67>0,F67<0),"Sí","No") -> No
B68: Atracos en el parque más cercano | C68: Hechos del entorno | D68: 2.9441098 | E68: -0.90826249 | F68: 6.5601897 | G68: 0.18525323 | H68: =IF(OR(E68>0,F68<0),"Sí","No") -> No
B69: Venta o consumo de drogas en el parque | C69: Hechos del entorno | D69: 4.3264657 | E69: 2.9668124 | F69: 6.346967 | G69: 4.7063302e-09 | H69: =IF(OR(E69>0,F69<0),"Sí","No") -> Sí
B70: No tiene parque cerca | C70: Hechos del entorno | D70: 1.0960096 | E70: -1.0052418 | F70: 2.9148768 | G70: 0.25443848 | H70: =IF(OR(E70>0,F70<0),"Sí","No") -> No
B71: Presenció acoso a mujeres | C71: Hechos del entorno | D71: 1.3232875 | E71: -1.6129843 | F71: 4.467729 | G71: 0.44388078 | H71: =IF(OR(E71>0,F71<0),"Sí","No") -> No
B72: Conflictos vecinales (de ninguno a todos) | C72: Hechos del entorno | D72: 1.0387069 | E72: -2.797067 | F72: 4.3803449 | G72: 0.65349223 | H72: =IF(OR(E72>0,F72<0),"Sí","No") -> No
B74: 5. Con efectos fijos de localidad
B75: Controla todo lo que es común a cada localidad (incluido su delito registrado). Se estiman 18 efectos fijos de localidad que no se muestran. Los hechos del entorno se mantienen.
B76: Variable | C76: Bloque | D76: Efecto marginal (pp) | E76: IC 95 % inferior | F76: IC 95 % superior | G76: p | H76: ¿IC excluye 0?
B77: Ser mujer | C77: Perfil | D77: -0.82914644 | E77: -4.521228 | F77: 3.3040889 | G77: 0.69487554 | H77: =IF(OR(E77>0,F77<0),"Sí","No") -> No
B78: Edad (por año) | C78: Perfil | D78: 0.031480352 | E78: -0.13967572 | F78: 0.15610587 | G78: 0.75431249 | H78: =IF(OR(E78>0,F78<0),"Sí","No") -> No
B79: Estrato (por nivel) | C79: Perfil | D79: -4.2464178 | E79: -8.2508501 | F79: -0.46354388 | G79: 0.046591982 | H79: =IF(OR(E79>0,F79<0),"Sí","No") -> Sí
B80: Vive en arriendo | C80: Perfil | D80: 2.7139914 | E80: -1.9739099 | F80: 6.7611735 | G80: 0.32942585 | H80: =IF(OR(E80>0,F80<0),"Sí","No") -> No
B81: Atracos en el parque más cercano | C81: Hechos del entorno | D81: 12.333329 | E81: 5.914024 | F81: 15.863144 | G81: 3.0609564e-06 | H81: =IF(OR(E81>0,F81<0),"Sí","No") -> Sí
B82: Venta o consumo de drogas en el parque | C82: Hechos del entorno | D82: -2.8017534 | E82: -7.757514 | F82: 4.4446277 | G82: 0.33498352 | H82: =IF(OR(E82>0,F82<0),"Sí","No") -> No
B83: No tiene parque cerca | C83: Hechos del entorno | D83: -7.0628424 | E83: -11.322475 | F83: -2.9567442 | G83: 0.0043447712 | H83: =IF(OR(E83>0,F83<0),"Sí","No") -> Sí
B84: Presenció acoso a mujeres | C84: Hechos del entorno | D84: 3.250441 | E84: -2.1880283 | F84: 9.3799353 | G84: 0.28871299 | H84: =IF(OR(E84>0,F84<0),"Sí","No") -> No
B85: Conflictos vecinales (de ninguno a todos) | C85: Hechos del entorno | D85: 15.428139 | E85: 5.3006709 | F85: 24.988865 | G85: 0.012281501 | H85: =IF(OR(E85>0,F85<0),"Sí","No") -> Sí
B87: 6. Modelo lineal con wild cluster bootstrap
B88: Modelo lineal de probabilidad con errores agrupados por localidad y p-valor por wild cluster bootstrap (pesos de Webb), robusto con pocos conglomerados.
B89: Variable | C89: Bloque | D89: Coeficiente (pp) | E89: p agrupado | F89: p wild bootstrap | G89: ¿p wild < 0,05?
B90: Hurtos en la localidad (+1.000 por 100 mil) | C90: Delito registrado | D90: -0.12693873 | E90: 0.91310198 | F90: 0.91891892 | G90: =IF(F90<0.05,"Sí","No") -> No
B91: Homicidios en la localidad (+1 por 100 mil) | C91: Delito registrado | D91: 0.47221026 | E91: 0.0053747972 | F91: 0.033033033 | G91: =IF(F91<0.05,"Sí","No") -> Sí
B92: Llamadas 123 por narcóticos (+100 por 100 mil) | C92: Delito registrado | D92: -0.3672603 | E92: 0.52463688 | F92: 0.54254254 | G92: =IF(F92<0.05,"Sí","No") -> No
B93: Atracos en el parque más cercano | C93: Hechos del entorno | D93: 13.290196 | E93: 4.9105242e-06 | F93: 0 | G93: =IF(F93<0.05,"Sí","No") -> Sí
B94: Conflictos vecinales (de ninguno a todos) | C94: Hechos del entorno | D94: 15.044018 | E94: 0.006682879 | F94: 0.046046046 | G94: =IF(F94<0.05,"Sí","No") -> Sí
B96: 7. Capacidad predictiva por bloques de variables | J96: AUC por bloque (eje desde 0,5 = azar)
B97: AUC fuera de muestra con validación cruzada estratificada repetida (25 pliegues). 0,5 = azar. Agregar el delito registrado casi no mejora la predicción; el entorno sí.
B98: Bloque de variables | C98: Composición (n.º de variables) | D98: AUC | E98: Desv. estándar | F98: Pliegues
B99: Perfil (sexo, edad, estrato, tenencia) | C99: Perfil (4) | D99: 0.60857857 | E99: 0.022877588 | F99: 25
B100: Perfil + delito registrado | C100: Perfil (4) + Delito registrado (3) | D100: 0.61132599 | E100: 0.02066016 | F100: 25
B101: Perfil + hechos del entorno | C101: Perfil (4) + Hechos del entorno (5) | D101: 0.65462771 | E101: 0.023635899 | F101: 25
B102: Perfil + hechos + delito | C102: Perfil (4) + Hechos del entorno (5) + Delito registrado (3) | D102: 0.65644798 | E102: 0.022964694 | F102: 25
B103: Perfil + calificación del entorno | C103: Perfil (4) + Calificación del entorno (2) | D103: 0.75482084 | E103: 0.016282977 | F103: 25
B104: Todo | C104: Perfil (4) + Delito registrado (3) + Hechos del entorno (5) + Calificación del entorno (2) | D104: 0.78249762 | E104: 0.017395953 | F104: 25
B106: Fuentes: outputs/tablas/m_hechos.csv, m_calif.csv, m_ciudad.csv, m_miedo.csv, m_efectos_fijos.csv, lpm_wild.csv y auc.csv (src/modelos.py). Las variables continuas se leen por la unidad indicada en su nombre (por ejemplo, +1.000 hurtos por 100 mil).

Sheet Genero
B1: EL MIEDO QUE NO BAJA · BOGOTÁ DATAJAM 5 · THE DATA SQUAD | M1: ← Portada
B2: Género
B3: A igual edad, estrato y victimización, las mujeres temen más y restringen más su vida (Encuesta Mundial de Valores 2024, Bogotá).
B6: 1. Mujeres frente a hombres
B7: Porcentajes ponderados de adultos de Bogotá (n = 1.824). Efecto de ser mujer: logit ponderado con edad, estrato y haber sido víctima; IC 95 % por bootstrap de localidades.
B8: Indicador (EMV 2024) | C8: Mujeres | D8: Hombres | E8: Diferencia (pp) | F8: Efecto de ser mujer (pp) | G8: IC 95 % inferior | H8: IC 95 % superior | I8: p | L8: Auxiliar del gráfico: error + | M8: Auxiliar del gráfico: error −
B9: Fue víctima de un delito (último año) | C9: 0.206 | D9: 0.284 | E9: =(C9-D9)*100 -> -7.8 | F9: Control del modelo
B10: No sale de noche | C10: 0.635 | D10: 0.572 | E10: =(C10-D10)*100 -> 6.3 | F10: 6.46829 | G10: 0.95961064 | H10: 11.504121 | I10: 0.024083904 | L10: =H10-F10 -> 5.0358311 | M10: =F10-G10 -> 5.5086793
B11: Teme acoso sexual | C11: 0.719 | D11: 0.539 | E11: =(C11-D11)*100 -> 18 | F11: 18.019705 | G11: 12.883317 | H11: 23.431944 | I11: 3.4379954e-09 | L11: =H11-F11 -> 5.4122387 | M11: =F11-G11 -> 5.1363886
B12: Siente inseguro su barrio | C12: 0.592 | D12: 0.518 | E12: =(C12-D12)*100 -> 7.4 | F12: 9.2810294 | G12: 5.048864 | H12: 13.891783 | I12: 0.00016842896 | L12: =H12-F12 -> 4.610754 | M12: =F12-G12 -> 4.2321655
B13: Haber sido víctima suma +19,5 pp a sentir inseguro el barrio (IC 95 % 12,8 a 25,0). Las mujeres reportan menos victimización y aun así temen más: el miedo no es solo experiencia de delito.
B15: Porcentaje de adultos por sexo | F15: Efecto de ser mujer, a igual victimización (pp)
B34: 2. Zona insegura y miedo en el espacio público, por sexo y localidad (Bienal 2025)
B35: Porcentajes ponderados de adultos. Ordenado por la diferencia en zona insegura.
B36: Localidad | C36: Zona insegura: mujeres | D36: Zona insegura: hombres | E36: Diferencia (pp) | F36: Miedo en espacio público: mujeres | G36: Miedo en espacio público: hombres | H36: Diferencia (pp)
B37: San Cristóbal | C37: 0.62384644 | D37: 0.48365453 | E37: =(C37-D37)*100 -> 14.019191 | F37: 0.10391685 | G37: 0.065564196 | H37: =(F37-G37)*100 -> 3.8352653
B38: Santa Fe | C38: 0.63763547 | D38: 0.52123749 | E38: =(C38-D38)*100 -> 11.639798 | F38: 0.12609411 | G38: 0.12210947 | H38: =(F38-G38)*100 -> 0.39846409
B39: Usaquén | C39: 0.28949644 | D39: 0.19805695 | E39: =(C39-D39)*100 -> 9.1439494 | F39: 0.10217712 | G39: 0.05080595 | H39: =(F39-G39)*100 -> 5.1371172
B40: Puente Aranda | C40: 0.4934753 | D40: 0.40912624 | E40: =(C40-D40)*100 -> 8.4349068 | F40: 0.13981318 | G40: 0.086628639 | H40: =(F40-G40)*100 -> 5.3184546
B41: Chapinero | C41: 0.53350855 | D41: 0.47363064 | E41: =(C41-D41)*100 -> 5.9877904 | F41: 0.13775002 | G41: 0.051701753 | H41: =(F41-G41)*100 -> 8.6048262
B42: Suba | C42: 0.42687843 | D42: 0.37930432 | E42: =(C42-D42)*100 -> 4.7574107 | F42: 0.16102024 | G42: 0.084259649 | H42: =(F42-G42)*100 -> 7.6760589
B43: Teusaquillo | C43: 0.38904245 | D43: 0.35463238 | E43: =(C43-D43)*100 -> 3.4410067 | F43: 0.11569971 | G43: 0.054472598 | H43: =(F43-G43)*100 -> 6.122711
B44: Los Mártires | C44: 0.40918532 | D44: 0.3786535 | E44: =(C44-D44)*100 -> 3.0531813 | F44: 0.13166013 | G44: 0.07615845 | H44: =(F44-G44)*100 -> 5.5501679
B45: La Candelaria | C45: 0.62497427 | D45: 0.59584314 | E45: =(C45-D45)*100 -> 2.9131129 | F45: 0.081628956 | G45: 0.10731198 | H45: =(F45-G45)*100 -> -2.5683022
B46: Barrios Unidos | C46: 0.48663475 | D46: 0.4585565 | E46: =(C46-D46)*100 -> 2.8078249 | F46: 0.13544346 | G46: 0.083103783 | H46: =(F46-G46)*100 -> 5.2339678
B47: Rafael Uribe Uribe | C47: 0.49567703 | D47: 0.4985655 | E47: =(C47-D47)*100 -> -0.28884724 | F47: 0.239599 | G47: 0.13186965 | H47: =(F47-G47)*100 -> 10.772935
B48: Engativá | C48: 0.47824794 | D48: 0.51153009 | E48: =(C48-D48)*100 -> -3.3282153 | F48: 0.087663302 | G48: 0.071072709 | H48: =(F48-G48)*100 -> 1.6590593
... B55: Tunjuelito | C55: 0.26672928 | D55: 0.45433044 | E55: =(C55-D55)*100 -> -18.760115 | F55: 0.13537086 | G55: 0.10785238 | H55: =(F55-G55)*100 -> 2.7518484
B57: 3. Modelos completos (logit ponderado, EMV 2024)
B58: Efectos marginales promedio de cada variable sobre cada resultado.
B59: Resultado · variable | C59: Efecto marginal (pp) | D59: IC 95 % inferior | E59: IC 95 % superior | F59: p | G59: ¿IC excluye 0?
B60: No sale de noche
B61: Ser mujer | C61: 6.46829 | D61: 0.95961064 | E61: 11.504121 | F61: 0.024083904 | G61: =IF(OR(D61>0,E61<0),"Sí","No") -> Sí
B62: Edad (por año) | C62: -0.0084536541 | D62: -0.14473063 | E62: 0.14597091 | F62: 0.91777681 | G62: =IF(OR(D62>0,E62<0),"Sí","No") -> No
B63: Estrato (por nivel) | C63: 1.5055407 | D63: -0.011106148 | E63: 3.904411 | F63: 0.12124271 | G63: =IF(OR(D63>0,E63<0),"Sí","No") -> No
B64: Fue víctima de un delito (último año) | C64: 2.452012 | D64: -2.9607624 | E64: 7.5996143 | F64: 0.34015075 | G64: =IF(OR(D64>0,E64<0),"Sí","No") -> No
B65: Teme acoso sexual
B66: Ser mujer | C66: 18.019705 | D66: 12.883317 | E66: 23.431944 | F66: 3.4379954e-09 | G66: =IF(OR(D66>0,E66<0),"Sí","No") -> Sí
B67: Edad (por año) | C67: -0.31917353 | D67: -0.45608202 | E67: -0.17748675 | F67: 1.6428413e-05 | G67: =IF(OR(D67>0,E67<0),"Sí","No") -> Sí
B68: Estrato (por nivel) | C68: 0.40011608 | D68: -2.0464307 | E68: 1.965821 | F68: 0.66375908 | G68: =IF(OR(D68>0,E68<0),"Sí","No") -> No
B69: Fue víctima de un delito (último año) | C69: 2.6948941 | D69: -1.6935945 | E69: 8.2915547 | F69: 0.31071021 | G69: =IF(OR(D69>0,E69<0),"Sí","No") -> No
B70: Siente inseguro su barrio
B71: Ser mujer | C71: 9.2810294 | D71: 5.048864 | E71: 13.891783 | F71: 0.00016842896 | G71: =IF(OR(D71>0,E71<0),"Sí","No") -> Sí
B72: Edad (por año) | C72: 0.49827179 | D72: 0.36344113 | E72: 0.67064389 | F72: 3.701301e-08 | G72: =IF(OR(D72>0,E72<0),"Sí","No") -> Sí
B73: Estrato (por nivel) | C73: -5.1024284 | D73: -7.6943231 | E73: -3.5258485 | F73: 1.5991757e-06 | G73: =IF(OR(D73>0,E73<0),"Sí","No") -> Sí
B74: Fue víctima de un delito (último año) | C74: 19.499488 | D74: 12.815493 | E74: 24.969544 | F74: 1.8200827e-09 | G74: =IF(OR(D74>0,E74<0),"Sí","No") -> Sí
B76: Fuentes: outputs/resultados.json (porcentajes por sexo), outputs/tablas/emv_*.csv y data/procesados/panel_localidad_2025.csv.

Sheet Serie_delitos
B1: EL MIEDO QUE NO BAJA · BOGOTÁ DATAJAM 5 · THE DATA SQUAD | N1: ← Portada
B2: Serie de delitos registrados
B3: Bogotá, enero-agosto de cada año (corte comparable que publica la SCJ; 2026 solo trae ese periodo). Suma de las 20 localidades.
B6: 1. Casos registrados (enero-agosto)
B7: Código | C7: Tipo de delito | D7: 2018 | E7: 2019 | F7: 2020 | G7: 2021 | H7: 2022 | I7: 2023 | J7: 2024 | K7: 2025 | L7: 2026 | M7: Cambio 2018 → 2026 | N7: Cambio 2019 → 2026
B8: HP | C8: Hurto a personas | D8: 170219 | E8: 210160 | F8: 128255 | G8: 159145 | H8: 178532 | I8: 106736 | J8: 85924 | K8: 84225 | L8: 73563 | M8: =IF(L8="","",L8/D8-1) -> -0.5678332 | N8: =IF(L8="","",L8/E8-1) -> -0.64996669
B9: HCE | C9: Hurto de celulares | D9: 5514 | E9: 5396 | F9: 4290 | G9: 6516 | H9: 6555 | I9: 3708 | J9: 3895 | K9: 3060 | L9: 2923 | M9: =IF(L9="","",L9/D9-1) -> -0.46989481 | N9: =IF(L9="","",L9/E9-1) -> -0.45830245
B10: HC | C10: Hurto a comercio | D10: 45079 | E10: 39779 | F10: 30342 | G10: 36621 | H10: 38042 | I10: 36932 | J10: 27120 | K10: 23027 | L10: 24374 | M10: =IF(L10="","",L10/D10-1) -> -0.45930478 | N10: =IF(L10="","",L10/E10-1) -> -0.38726464
B11: HR | C11: Hurto a residencias | D11: 19486 | E11: 18624 | F11: 15904 | G11: 15121 | H11: 9866 | I11: 5518 | J11: 4171 | K11: 4014 | L11: 4289 | M11: =IF(L11="","",L11/D11-1) -> -0.77989326 | N11: =IF(L11="","",L11/E11-1) -> -0.76970576
B12: HA | C12: Hurto de automotores | D12: 4826 | E12: 4876 | F12: 4054 | G12: 4682 | H12: 4675 | I12: 2800 | J12: 2945 | K12: 2176 | L12: 2029 | M12: =IF(L12="","",L12/D12-1) -> -0.579569 | N12: =IF(L12="","",L12/E12-1) -> -0.58388023
B13: HM | C13: Hurto de motocicletas | D13: 27634 | E13: 27347 | F13: 18012 | G13: 17337 | H13: 15453 | I13: 9033 | J13: 7766 | K13: 6296 | L13: 5805 | M13: =IF(L13="","",L13/D13-1) -> -0.78993269 | N13: =IF(L13="","",L13/E13-1) -> -0.78772809
B14: HB | C14: Hurto de bicicletas | D14: 5349 | E14: 5226 | F14: 7148 | G14: 6738 | H14: 5560 | I14: 5428 | J14: 5193 | K14: 4661 | L14: 5133 | M14: =IF(L14="","",L14/D14-1) -> -0.04038138 | N14: =IF(L14="","",L14/E14-1) -> -0.017795637
B15: H | C15: Homicidios | D15: 684 | E15: 656 | F15: 654 | G15: 763 | H15: 658 | I15: 712 | J15: 747 | K15: 799 | L15: 740 | M15: =IF(L15="","",L15/D15-1) -> 0.081871345 | N15: =IF(L15="","",L15/E15-1) -> 0.12804878
B16: LP | C16: Lesiones personales | D16: 19167 | E16: 15830 | F16: 9998 | G16: 14811 | H16: 13855 | I16: 12438 | J16: 12140 | K16: 12431 | M16: =IF(L16="","",L16/D16-1) | N16: =IF(L16="","",L16/E16-1)
B17: VI | C17: Violencia intrafamiliar | D17: 23854 | E17: 23165 | F17: 24501 | G17: 23157 | H17: 23085 | I17: 20251 | J17: 26870 | K17: 29440 | L17: 34859 | M17: =IF(L17="","",L17/D17-1) -> 0.4613482 | N17: =IF(L17="","",L17/E17-1) -> 0.5048133
B18: DS | C18: Delitos sexuales | D18: 3593 | E18: 4167 | F18: 3209 | G18: 3955 | H18: 4575 | I18: 3906 | J18: 6433 | K18: 5981 | L18: 5224 | M18: =IF(L18="","",L18/D18-1) -> 0.45393821 | N18: =IF(L18="","",L18/E18-1) -> 0.25365971
B19: Lesiones personales no tiene dato publicado para 2026. Fuente: SCJ, Delito de alto impacto (data/procesados/scj_delitos_localidad_largo.csv). Azul: baja; vino: sube.
B21: 2. Índice 2018 = 100: el hurto baja; la violencia intrafamiliar y los delitos sexuales suben
B43: 3. Índice 2018 = 100 (fórmulas sobre la tabla 1)
B44: Código | C44: Tipo de delito | D44: 2018 | E44: 2019 | F44: 2020 | G44: 2021 | H44: 2022 | I44: 2023 | J44: 2024 | K44: 2025 | L44: 2026
B45: HP | C45: Hurto a personas | D45: =IF(D8="","",D8/$D8*100) -> 100 | E45: =IF(E8="","",E8/$D8*100) -> 123.46448 | F45: =IF(F8="","",F8/$D8*100) -> 75.347053 | G45: =IF(G8="","",G8/$D8*100) -> 93.494263 | H45: =IF(H8="","",H8/$D8*100) -> 104.88371 | I45: =IF(I8="","",I8/$D8*100) -> 62.705103 | J45: =IF(J8="","",J8/$D8*100) -> 50.478501 | K45: =IF(K8="","",K8/$D8*100) -> 49.480375 | L45: =IF(L8="","",L8/$D8*100) -> 43.21668
B46: HCE | C46: Hurto de celulares | D46: =IF(D9="","",D9/$D9*100) -> 100 | E46: =IF(E9="","",E9/$D9*100) -> 97.859993 | F46: =IF(F9="","",F9/$D9*100) -> 77.801959 | G46: =IF(G9="","",G9/$D9*100) -> 118.17193 | H46: =IF(H9="","",H9/$D9*100) -> 118.87922 | I46: =IF(I9="","",I9/$D9*100) -> 67.247008 | J46: =IF(J9="","",J9/$D9*100) -> 70.638375 | K46: =IF(K9="","",K9/$D9*100) -> 55.495103 | L46: =IF(L9="","",L9/$D9*100) -> 53.010519
B47: HC | C47: Hurto a comercio | D47: =IF(D10="","",D10/$D10*100) -> 100 | E47: =IF(E10="","",E10/$D10*100) -> 88.242863 | F47: =IF(F10="","",F10/$D10*100) -> 67.308503 | G47: =IF(G10="","",G10/$D10*100) -> 81.237383 | H47: =IF(H10="","",H10/$D10*100) -> 84.389627 | I47: =IF(I10="","",I10/$D10*100) -> 81.927283 | J47: =IF(J10="","",J10/$D10*100) -> 60.161051 | K47: =IF(K10="","",K10/$D10*100) -> 51.081435 | L47: =IF(L10="","",L10/$D10*100) -> 54.069522
B48: HR | C48: Hurto a residencias | D48: =IF(D11="","",D11/$D11*100) -> 100 | E48: =IF(E11="","",E11/$D11*100) -> 95.576311 | F48: =IF(F11="","",F11/$D11*100) -> 81.617572 | G48: =IF(G11="","",G11/$D11*100) -> 77.599302 | H48: =IF(H11="","",H11/$D11*100) -> 50.631222 | I48: =IF(I11="","",I11/$D11*100) -> 28.317767 | J48: =IF(J11="","",J11/$D11*100) -> 21.405111 | K48: =IF(K11="","",K11/$D11*100) -> 20.599405 | L48: =IF(L11="","",L11/$D11*100) -> 22.010674
B49: HA | C49: Hurto de automotores | D49: =IF(D12="","",D12/$D12*100) -> 100 | E49: =IF(E12="","",E12/$D12*100) -> 101.03605 | F49: =IF(F12="","",F12/$D12*100) -> 84.003315 | G49: =IF(G12="","",G12/$D12*100) -> 97.016162 | H49: =IF(H12="","",H12/$D12*100) -> 96.871115 | I49: =IF(I12="","",I12/$D12*100) -> 58.019063 | J49: =IF(J12="","",J12/$D12*100) -> 61.023622 | K49: =IF(K12="","",K12/$D12*100) -> 45.089101 | L49: =IF(L12="","",L12/$D12*100) -> 42.0431
B50: HM | C50: Hurto de motocicletas | D50: =IF(D13="","",D13/$D13*100) -> 100 | E50: =IF(E13="","",E13/$D13*100) -> 98.961424 | F50: =IF(F13="","",F13/$D13*100) -> 65.180575 | G50: =IF(G13="","",G13/$D13*100) -> 62.737932 | H50: =IF(H13="","",H13/$D13*100) -> 55.920243 | I50: =IF(I13="","",I13/$D13*100) -> 32.687993 | J50: =IF(J13="","",J13/$D13*100) -> 28.103061 | K50: =IF(K13="","",K13/$D13*100) -> 22.783528 | L50: =IF(L13="","",L13/$D13*100) -> 21.006731
B51: HB | C51: Hurto de bicicletas | D51: =IF(D14="","",D14/$D14*100) -> 100 | E51: =IF(E14="","",E14/$D14*100) -> 97.700505 | F51: =IF(F14="","",F14/$D14*100) -> 133.63245 | G51: =IF(G14="","",G14/$D14*100) -> 125.96747 | H51: =IF(H14="","",H14/$D14*100) -> 103.94466 | I51: =IF(I14="","",I14/$D14*100) -> 101.47691 | J51: =IF(J14="","",J14/$D14*100) -> 97.083567 | K51: =IF(K14="","",K14/$D14*100) -> 87.137783 | L51: =IF(L14="","",L14/$D14*100) -> 95.961862
B52: H | C52: Homicidios | D52: =IF(D15="","",D15/$D15*100) -> 100 | E52: =IF(E15="","",E15/$D15*100) -> 95.906433 | F52: =IF(F15="","",F15/$D15*100) -> 95.614035 | G52: =IF(G15="","",G15/$D15*100) -> 111.54971 | H52: =IF(H15="","",H15/$D15*100) -> 96.19883 | I52: =IF(I15="","",I15/$D15*100) -> 104.09357 | J52: =IF(J15="","",J15/$D15*100) -> 109.21053 | K52: =IF(K15="","",K15/$D15*100) -> 116.81287 | L52: =IF(L15="","",L15/$D15*100) -> 108.18713
B53: LP | C53: Lesiones personales | D53: =IF(D16="","",D16/$D16*100) -> 100 | E53: =IF(E16="","",E16/$D16*100) -> 82.589868 | F53: =IF(F16="","",F16/$D16*100) -> 52.162571 | G53: =IF(G16="","",G16/$D16*100) -> 77.273439 | H53: =IF(H16="","",H16/$D16*100) -> 72.285699 | I53: =IF(I16="","",I16/$D16*100) -> 64.892784 | J53: =IF(J16="","",J16/$D16*100) -> 63.338029 | K53: =IF(K16="","",K16/$D16*100) -> 64.856263 | L53: =IF(L16="","",L16/$D16*100)
B54: VI | C54: Violencia intrafamiliar | D54: =IF(D17="","",D17/$D17*100) -> 100 | E54: =IF(E17="","",E17/$D17*100) -> 97.111596 | F54: =IF(F17="","",F17/$D17*100) -> 102.71233 | G54: =IF(G17="","",G17/$D17*100) -> 97.078058 | H54: =IF(H17="","",H17/$D17*100) -> 96.776222 | I54: =IF(I17="","",I17/$D17*100) -> 84.895615 | J54: =IF(J17="","",J17/$D17*100) -> 112.64358 | K54: =IF(K17="","",K17/$D17*100) -> 123.41746 | L54: =IF(L17="","",L17/$D17*100) -> 146.13482
B55: DS | C55: Delitos sexuales | D55: =IF(D18="","",D18/$D18*100) -> 100 | E55: =IF(E18="","",E18/$D18*100) -> 115.97551 | F55: =IF(F18="","",F18/$D18*100) -> 89.312552 | G55: =IF(G18="","",G18/$D18*100) -> 110.07515 | H55: =IF(H18="","",H18/$D18*100) -> 127.33092 | I55: =IF(I18="","",I18/$D18*100) -> 108.71138 | J55: =IF(J18="","",J18/$D18*100) -> 179.04258 | K55: =IF(K18="","",K18/$D18*100) -> 166.46257 | L55: =IF(L18="","",L18/$D18*100) -> 145.39382
B56: Cada celda = casos del año / casos de 2018 × 100. Más de 100: sube frente a 2018 (rosado); menos de 100: baja (azul).

Sheet Simulador
B1: EL MIEDO QUE NO BAJA · BOGOTÁ DATAJAM 5 · THE DATA SQUAD | P1: ← Portada
B2: Simulador de escenarios
B3: ¿Cuánto bajaría la inseguridad percibida si mejoran el alumbrado y los parques? Cambia las celdas crema: todo se recalcula.
B6: 1. PALANCAS | I6: BOGOTÁ · PROBABILIDAD DE SENTIR INSEGURA LA ZONA
B7: Zonas donde el alumbrado deja de ser malo | F7: 0.5 | I7: Hoy (modelo) | L7: Escenario | O7: Cambio
B8: Parques donde dejan de verse atracos | F8: 0.5 | I8: =D14 -> 0.48389448 | K8: → | L8: =E14 -> 0.40986598 | O8: =F14 -> -7.4028502
B9: Grupo de población | F9: Total | I9: Adultos que dejarían de sentir insegura su zona (orden de magnitud, solo para el total) | O9: =IF(grupo_sim="Total",-F14/100*$P$10,"n. a.") -> 467002.74
B10: Celdas crema: editables. Coberturas de 0 % a 100 %; grupo: Total, Mujeres u Hombres (lista desplegable). | I10: Adultos urbanos representados por la Bienal 2025 (factor de expansión) | P10: 6308418
B12: 2. RESULTADO POR LOCALIDAD · PROBABILIDAD DE SENTIR INSEGURA LA ZONA | I12: CAMBIO POR LOCALIDAD (pp), DE LA MAYOR BAJA A LA MENOR
B13: Código | C13: Localidad | D13: Hoy (modelo) | E13: Escenario | F13: Cambio (pp) | G13: Observado (Bienal 2025) | R13: Clave de orden | S13: Puesto | T13: Auxiliar del gráfico: localidad | U13: Auxiliar: cambio (pp)
C14: Bogotá | D14: =SUMIFS(Datos_escenarios!$E$8:$E$67,Datos_escenarios!$B$8:$B$67,grupo_sim,Datos_escenarios!$C$8:$C$67,0) -> 0.48389448 | E14: =(1-f_alumbrado)*(1-f_parques)*D14+f_alumbrado*(1-f_parques)*SUMIFS(Datos_escenarios!$F$8:$F$67,Datos_escenarios!$B$8:$B$67,grupo_sim,Datos_escenarios!$C$8:$C$67,0)+(1-f_alumbrado)*f_parques*SUMIFS(Datos_escenarios!$G$8:$G$67,Datos_escenarios!$B$8:$B$67,grupo_sim,Datos_escenarios!$C$8:$C$67,0)+f_alumbrado*f_parques*SUMIFS(Datos_escenarios!$H$8:$H$67,Datos_escenarios!$B$8:$B$67,grupo_sim,Datos_escenarios!$C$8:$C$67,0) -> 0.40986598 | F14: =(E14-D14)*100 -> -7.4028502 | G14: =SUMIFS(Datos_escenarios!$I$8:$I$67,Datos_escenarios!$B$8:$B$67,grupo_sim,Datos_escenarios!$C$8:$C$67,0) -> 0.48389448
B15: 1 | C15: Usaquén | D15: =SUMIFS(Datos_escenarios!$E$8:$E$67,Datos_escenarios!$B$8:$B$67,grupo_sim,Datos_escenarios!$C$8:$C$67,$B15) -> 0.32590431 | E15: =(1-f_alumbrado)*(1-f_parques)*D15+f_alumbrado*(1-f_parques)*SUMIFS(Datos_escenarios!$F$8:$F$67,Datos_escenarios!$B$8:$B$67,grupo_sim,Datos_escenarios!$C$8:$C$67,$B15)+(1-f_alumbrado)*f_parques*SUMIFS(Datos_escenarios!$G$8:$G$67,Datos_escenarios!$B$8:$B$67,grupo_sim,Datos_escenarios!$C$8:$C$67,$B15)+f_alumbrado*f_parques*SUMIFS(Datos_escenarios!$H$8:$H$67,Datos_escenarios!$B$8:$B$67,grupo_sim,Datos_escenarios!$C$8:$C$67,$B15) -> 0.25742811 | F15: =(E15-D15)*100 -> -6.8476203 | G15: =SUMIFS(Datos_escenarios!$I$8:$I$67,Datos_escenarios!$B$8:$B$67,grupo_sim,Datos_escenarios!$C$8:$C$67,$B15) -> 0.24820972 | R15: =F15+B15/10000000 -> -6.8476202 | S15: 1 | T15: =INDEX($C$15:$C$33,MATCH(SMALL($R$15:$R$33,S15),$R$15:$R$33,0)) -> La Candelaria | U15: =INDEX($F$15:$F$33,MATCH(SMALL($R$15:$R$33,S15),$R$15:$R$33,0)) -> -11.673064
B16: 2 | C16: Chapinero | D16: =SUMIFS(Datos_escenarios!$E$8:$E$67,Datos_escenarios!$B$8:$B$67,grupo_sim,Datos_escenarios!$C$8:$C$67,$B16) -> 0.40470974 | E16: =(1-f_alumbrado)*(1-f_parques)*D16+f_alumbrado*(1-f_parques)*SUMIFS(Datos_escenarios!$F$8:$F$67,Datos_escenarios!$B$8:$B$67,grupo_sim,Datos_escenarios!$C$8:$C$67,$B16)+(1-f_alumbrado)*f_parques*SUMIFS(Datos_escenarios!$G$8:$G$67,Datos_escenarios!$B$8:$B$67,grupo_sim,Datos_escenarios!$C$8:$C$67,$B16)+f_alumbrado*f_parques*SUMIFS(Datos_escenarios!$H$8:$H$67,Datos_escenarios!$B$8:$B$67,grupo_sim,Datos_escenarios!$C$8:$C$67,$B16) -> 0.33360005 | F16: =(E16-D16)*100 -> -7.1109696 | G16: =SUMIFS(Datos_escenarios!$I$8:$I$67,Datos_escenarios!$B$8:$B$67,grupo_sim,Datos_escenarios!$C$8:$C$67,$B16) -> 0.50505065 | R16: =F16+B16/10000000 -> -7.1109694 | S16: 2 | T16: =INDEX($C$15:$C$33,MATCH(SMALL($R$15:$R$33,S16),$R$15:$R$33,0)) -> Tunjuelito | U16: =INDEX($F$15:$F$33,MATCH(SMALL($R$15:$R$33,S16),$R$15:$R$33,0)) -> -10.67582
B17: 3 | C17: Santa Fe | D17: =SUMIFS(Datos_escenarios!$E$8:$E$67,Datos_escenarios!$B$8:$B$67,grupo_sim,Datos_escenarios!$C$8:$C$67,$B17) -> 0.64535982 | E17: =(1-f_alumbrado)*(1-f_parques)*D17+f_alumbrado*(1-f_parques)*SUMIFS(Datos_escenarios!$F$8:$F$67,Datos_escenarios!$B$8:$B$67,grupo_sim,Datos_escenarios!$C$8:$C$67,$B17)+(1-f_alumbrado)*f_parques*SUMIFS(Datos_escenarios!$G$8:$G$67,Datos_escenarios!$B$8:$B$67,grupo_sim,Datos_escenarios!$C$8:$C$67,$B17)+f_alumbrado*f_parques*SUMIFS(Datos_escenarios!$H$8:$H$67,Datos_escenarios!$B$8:$B$67,grupo_sim,Datos_escenarios!$C$8:$C$67,$B17) -> 0.55355054 | F17: =(E17-D17)*100 -> -9.1809281 | G17: =SUMIFS(Datos_escenarios!$I$8:$I$67,Datos_escenarios!$B$8:$B$67,grupo_sim,Datos_escenarios!$C$8:$C$67,$B17) -> 0.58063905 | R17: =F17+B17/10000000 -> -9.1809278 | S17: 3 | T17: =INDEX($C$15:$C$33,MATCH(SMALL($R$15:$R$33,S17),$R$15:$R$33,0)) -> Ciudad Bolívar | U17: =INDEX($F$15:$F$33,MATCH(SMALL($R$15:$R$33,S17),$R$15:$R$33,0)) -> -10.216964
B18: 4 | C18: San Cristóbal | D18: =SUMIFS(Datos_escenarios!$E$8:$E$67,Datos_escenarios!$B$8:$B$67,grupo_sim,Datos_escenarios!$C$8:$C$67,$B18) -> 0.51234963 | E18: =(1-f_alumbrado)*(1-f_parques)*D18+f_alumbrado*(1-f_parques)*SUMIFS(Datos_escenarios!$F$8:$F$67,Datos_escenarios!$B$8:$B$67,grupo_sim,Datos_escenarios!$C$8:$C$67,$B18)+(1-f_alumbrado)*f_parques*SUMIFS(Datos_escenarios!$G$8:$G$67,Datos_escenarios!$B$8:$B$67,grupo_sim,Datos_escenarios!$C$8:$C$67,$B18)+f_alumbrado*f_parques*SUMIFS(Datos_escenarios!$H$8:$H$67,Datos_escenarios!$B$8:$B$67,grupo_sim,Datos_escenarios!$C$8:$C$67,$B18) -> 0.44015379 | F18: =(E18-D18)*100 -> -7.2195833 | G18: =SUMIFS(Datos_escenarios!$I$8:$I$67,Datos_escenarios!$B$8:$B$67,grupo_sim,Datos_escenarios!$C$8:$C$67,$B18) -> 0.55734341 | R18: =F18+B18/10000000 -> -7.2195829 | S18: 4 | T18: =INDEX($C$15:$C$33,MATCH(SMALL($R$15:$R$33,S18),$R$15:$R$33,0)) -> Santa Fe | U18: =INDEX($F$15:$F$33,MATCH(SMALL($R$15:$R$33,S18),$R$15:$R$33,0)) -> -9.1809281
B19: 5 | C19: Usme | D19: =SUMIFS(Datos_escenarios!$E$8:$E$67,Datos_escenarios!$B$8:$B$67,grupo_sim,Datos_escenarios!$C$8:$C$67,$B19) -> 0.5686295 | E19: =(1-f_alumbrado)*(1-f_parques)*D19+f_alumbrado*(1-f_parques)*SUMIFS(Datos_escenarios!$F$8:$F$67,Datos_escenarios!$B$8:$B$67,grupo_sim,Datos_escenarios!$C$8:$C$67,$B19)+(1-f_alumbrado)*f_parques*SUMIFS(Datos_escenarios!$G$8:$G$67,Datos_escenarios!$B$8:$B$67,grupo_sim,Datos_escenarios!$C$8:$C$67,$B19)+f_alumbrado*f_parques*SUMIFS(Datos_escenarios!$H$8:$H$67,Datos_escenarios!$B$8:$B$67,grupo_sim,Datos_escenarios!$C$8:$C$67,$B19) -> 0.47702184 | F19: =(E19-D19)*100 -> -9.1607654 | G19: =SUMIFS(Datos_escenarios!$I$8:$I$67,Datos_escenarios!$B$8:$B$67,grupo_sim,Datos_escenarios!$C$8:$C$67,$B19) -> 0.64641785 | R19: =F19+B19/10000000 -> -9.1607649 | S19: 5 | T19: =INDEX($C$15:$C$33,MATCH(SMALL($R$15:$R$33,S19),$R$15:$R$33,0)) -> Usme | U19: =INDEX($F$15:$F$33,MATCH(SMALL($R$15:$R$33,S19),$R$15:$R$33,0)) -> -9.1607654
B20: 6 | C20: Tunjuelito | D20: =SUMIFS(Datos_escenarios!$E$8:$E$67,Datos_escenarios!$B$8:$B$67,grupo_sim,Datos_escenarios!$C$8:$C$67,$B20) -> 0.50741372 | E20: =(1-f_alumbrado)*(1-f_parques)*D20+f_alumbrado*(1-f_parques)*SUMIFS(Datos_escenarios!$F$8:$F$67,Datos_escenarios!$B$8:$B$67,grupo_sim,Datos_escenarios!$C$8:$C$67,$B20)+(1-f_alumbrado)*f_parques*SUMIFS(Datos_escenarios!$G$8:$G$67,Datos_escenarios!$B$8:$B$67,grupo_sim,Datos_escenarios!$C$8:$C$67,$B20)+f_alumbrado*f_parques*SUMIFS(Datos_escenarios!$H$8:$H$67,Datos_escenarios!$B$8:$B$67,grupo_sim,Datos_escenarios!$C$8:$C$67,$B20) -> 0.40065552 | F20: =(E20-D20)*100 -> -10.67582 | G20: =SUMIFS(Datos_escenarios!$I$8:$I$67,Datos_escenarios!$B$8:$B$67,grupo_sim,Datos_escenarios!$C$8:$C$67,$B20) -> 0.3598543 | R20: =F20+B20/10000000 -> -10.675819 | S20: 6 | T20: =INDEX($C$15:$C$33,MATCH(SMALL($R$15:$R$33,S20),$R$15:$R$33,0)) -> Los Mártires | U20: =INDEX($F$15:$F$33,MATCH(SMALL($R$15:$R$33,S20),$R$15:$R$33,0)) -> -9.0948905
B21: 7 | C21: Bosa | D21: =SUMIFS(Datos_escenarios!$E$8:$E$67,Datos_escenarios!$B$8:$B$67,grupo_sim,Datos_escenarios!$C$8:$C$67,$B21) -> 0.55975086 | E21: =(1-f_alumbrado)*(1-f_parques)*D21+f_alumbrado*(1-f_parques)*SUMIFS(Datos_escenarios!$F$8:$F$67,Datos_escenarios!$B$8:$B$67,grupo_sim,Datos_escenarios!$C$8:$C$67,$B21)+(1-f_alumbrado)*f_parques*SUMIFS(Datos_escenarios!$G$8:$G$67,Datos_escenarios!$B$8:$B$67,grupo_sim,Datos_escenarios!$C$8:$C$67,$B21)+f_alumbrado*f_parques*SUMIFS(Datos_escenarios!$H$8:$H$67,Datos_escenarios!$B$8:$B$67,grupo_sim,Datos_escenarios!$C$8:$C$67,$B21) -> 0.47183028 | F21: =(E21-D21)*100 -> -8.792058 | G21: =SUMIFS(Datos_escenarios!$I$8:$I$67,Datos_escenarios!$B$8:$B$67,grupo_sim,Datos_escenarios!$C$8:$C$67,$B21) -> 0.57061377 | R21: =F21+B21/10000000 -> -8.7920573 | S21: 7 | T21: =INDEX($C$15:$C$33,MATCH(SMALL($R$15:$R$33,S21),$R$15:$R$33,0)) -> Bosa | U21: =INDEX($F$15:$F$33,MATCH(SMALL($R$15:$R$33,S21),$R$15:$R$33,0)) -> -8.792058
B22: 8 | C22: Kennedy | D22: =SUMIFS(Datos_escenarios!$E$8:$E$67,Datos_escenarios!$B$8:$B$67,grupo_sim,Datos_escenarios!$C$8:$C$67,$B22) -> 0.49095758 | E22: =(1-f_alumbrado)*(1-f_parques)*D22+f_alumbrado*(1-f_parques)*SUMIFS(Datos_escenarios!$F$8:$F$67,Datos_escenarios!$B$8:$B$67,grupo_sim,Datos_escenarios!$C$8:$C$67,$B22)+(1-f_alumbrado)*f_parques*SUMIFS(Datos_escenarios!$G$8:$G$67,Datos_escenarios!$B$8:$B$67,grupo_sim,Datos_escenarios!$C$8:$C$67,$B22)+f_alumbrado*f_parques*SUMIFS(Datos_escenarios!$H$8:$H$67,Datos_escenarios!$B$8:$B$67,grupo_sim,Datos_escenarios!$C$8:$C$67,$B22) -> 0.41005658 | F22: =(E22-D22)*100 -> -8.0900997 | G22: =SUMIFS(Datos_escenarios!$I$8:$I$67,Datos_escenarios!$B$8:$B$67,grupo_sim,Datos_escenarios!$C$8:$C$67,$B22) -> 0.58445401 | R22: =F22+B22/10000000 -> -8.0900989 | S22: 8 | T22: =INDEX($C$15:$C$33,MATCH(SMALL($R$15:$R$33,S22),$R$15:$R$33,0)) -> Kennedy | U22: =INDEX($F$15:$F$33,MATCH(SMALL($R$15:$R$33,S22),$R$15:$R$33,0)) -> -8.0900997
B23: 9 | C23: Fontibón | D23: =SUMIFS(Datos_escenarios!$E$8:$E$67,Datos_escenarios!$B$8:$B$67,grupo_sim,Datos_escenarios!$C$8:$C$67,$B23) -> 0.38406274 | E23: =(1-f_alumbrado)*(1-f_parques)*D23+f_alumbrado*(1-f_parques)*SUMIFS(Datos_escenarios!$F$8:$F$67,Datos_escenarios!$B$8:$B$67,grupo_sim,Datos_escenarios!$C$8:$C$67,$B23)+(1-f_alumbrado)*f_parques*SUMIFS(Datos_escenarios!$G$8:$G$67,Datos_escenarios!$B$8:$B$67,grupo_sim,Datos_escenarios!$C$8:$C$67,$B23)+f_alumbrado*f_parques*SUMIFS(Datos_escenarios!$H$8:$H$67,Datos_escenarios!$B$8:$B$67,grupo_sim,Datos_escenarios!$C$8:$C$67,$B23) -> 0.31862911 | F23: =(E23-D23)*100 -> -6.5433625 | G23: =SUMIFS(Datos_escenarios!$I$8:$I$67,Datos_escenarios!$B$8:$B$67,grupo_sim,Datos_escenarios!$C$8:$C$67,$B23) -> 0.27087933 | R23: =F23+B23/10000000 -> -6.5433616 | S23: 9 | T23: =INDEX($C$15:$C$33,MATCH(SMALL($R$15:$R$33,S23),$R$15:$R$33,0)) -> Engativá | U23: =INDEX($F$15:$F$33,MATCH(SMALL($R$15:$R$33,S23),$R$15:$R$33,0)) -> -7.4746901
B24: 10 | C24: Engativá | D24: =SUMIFS(Datos_escenarios!$E$8:$E$67,Datos_escenarios!$B$8:$B$67,grupo_sim,Datos_escenarios!$C$8:$C$67,$B24) -> 0.47317427 | E24: =(1-f_alumbrado)*(1-f_parques)*D24+f_alumbrado*(1-f_parques)*SUMIFS(Datos_escenarios!$F$8:$F$67,Datos_escenarios!$B$8:$B$67,grupo_sim,Datos_escenarios!$C$8:$C$67,$B24)+(1-f_alumbrado)*f_parques*SUMIFS(Datos_escenarios!$G$8:$G$67,Datos_escenarios!$B$8:$B$67,grupo_sim,Datos_escenarios!$C$8:$C$67,$B24)+f_alumbrado*f_parques*SUMIFS(Datos_escenarios!$H$8:$H$67,Datos_escenarios!$B$8:$B$67,grupo_sim,Datos_escenarios!$C$8:$C$67,$B24) -> 0.39842737 | F24: =(E24-D24)*100 -> -7.4746901 | G24: =SUMIFS(Datos_escenarios!$I$8:$I$67,Datos_escenarios!$B$8:$B$67,grupo_sim,Datos_escenarios!$C$8:$C$67,$B24) -> 0.4939223 | R24: =F24+B24/10000000 -> -7.4746891 | S24: 10 | T24: =INDEX($C$15:$C$33,MATCH(SMALL($R$15:$R$33,S24),$R$15:$R$33,0)) -> Antonio Nariño | U24: =INDEX($F$15:$F$33,MATCH(SMALL($R$15:$R$33,S24),$R$15:$R$33,0)) -> -7.2398278
B25: 11 | C25: Suba | D25: =SUMIFS(Datos_escenarios!$E$8:$E$67,Datos_escenarios!$B$8:$B$67,grupo_sim,Datos_escenarios!$C$8:$C$67,$B25) -> 0.45139816 | E25: =(1-f_alumbrado)*(1-f_parques)*D25+f_alumbrado*(1-f_parques)*SUMIFS(Datos_escenarios!$F$8:$F$67,Datos_escenarios!$B$8:$B$67,grupo_sim,Datos_escenarios!$C$8:$C$67,$B25)+(1-f_alumbrado)*f_parques*SUMIFS(Datos_escenarios!$G$8:$G$67,Datos_escenarios!$B$8:$B$67,grupo_sim,Datos_escenarios!$C$8:$C$67,$B25)+f_alumbrado*f_parques*SUMIFS(Datos_escenarios!$H$8:$H$67,Datos_escenarios!$B$8:$B$67,grupo_sim,Datos_escenarios!$C$8:$C$67,$B25) -> 0.40057091 | F25: =(E25-D25)*100 -> -5.0827249 | G25: =SUMIFS(Datos_escenarios!$I$8:$I$67,Datos_escenarios!$B$8:$B$67,grupo_sim,Datos_escenarios!$C$8:$C$67,$B25) -> 0.40472664 | R25: =F25+B25/10000000 -> -5.0827238 | S25: 11 | T25: =INDEX($C$15:$C$33,MATCH(SMALL($R$15:$R$33,S25),$R$15:$R$33,0)) -> San Cristóbal | U25: =INDEX($F$15:$F$33,MATCH(SMALL($R$15:$R$33,S25),$R$15:$R$33,0)) -> -7.2195833
B26: 12 | C26: Barrios Unidos | D26: =SUMIFS(Datos_escenarios!$E$8:$E$67,Datos_escenarios!$B$8:$B$67,grupo_sim,Datos_escenarios!$C$8:$C$67,$B26) -> 0.42574606 | E26: =(1-f_alumbrado)*(1-f_parques)*D26+f_alumbrado*(1-f_parques)*SUMIFS(Datos_escenarios!$F$8:$F$67,Datos_escenarios!$B$8:$B$67,grupo_sim,Datos_escenarios!$C$8:$C$67,$B26)+(1-f_alumbrado)*f_parques*SUMIFS(Datos_escenarios!$G$8:$G$67,Datos_escenarios!$B$8:$B$67,grupo_sim,Datos_escenarios!$C$8:$C$67,$B26)+f_alumbrado*f_parques*SUMIFS(Datos_escenarios!$H$8:$H$67,Datos_escenarios!$B$8:$B$67,grupo_sim,Datos_escenarios!$C$8:$C$67,$B26) -> 0.3683441 | F26: =(E26-D26)*100 -> -5.7401957 | G26: =SUMIFS(Datos_escenarios!$I$8:$I$67,Datos_escenarios!$B$8:$B$67,grupo_sim,Datos_escenarios!$C$8:$C$67,$B26) -> 0.47263052 | R26: =F26+B26/10000000 -> -5.7401945 | S26: 12 | T26: =INDEX($C$15:$C$33,MATCH(SMALL($R$15:$R$33,S26),$R$15:$R$33,0)) -> Chapinero | U26: =INDEX($F$15:$F$33,MATCH(SMALL($R$15:$R$33,S26),$R$15:$R$33,0)) -> -7.1109696
... B33: 19 | C33: Ciudad Bolívar | D33: =SUMIFS(Datos_escenarios!$E$8:$E$67,Datos_escenarios!$B$8:$B$67,grupo_sim,Datos_escenarios!$C$8:$C$67,$B33) -> 0.66761075 | E33: =(1-f_alumbrado)*(1-f_parques)*D33+f_alumbrado*(1-f_parques)*SUMIFS(Datos_escenarios!$F$8:$F$67,Datos_escenarios!$B$8:$B$67,grupo_sim,Datos_escenarios!$C$8:$C$67,$B33)+(1-f_alumbrado)*f_parques*SUMIFS(Datos_escenarios!$G$8:$G$67,Datos_escenarios!$B$8:$B$67,grupo_sim,Datos_escenarios!$C$8:$C$67,$B33)+f_alumbrado*f_parques*SUMIFS(Datos_escenarios!$H$8:$H$67,Datos_escenarios!$B$8:$B$67,grupo_sim,Datos_escenarios!$C$8:$C$67,$B33) -> 0.5654411 | F33: =(E33-D33)*100 -> -10.216964 | G33: =SUMIFS(Datos_escenarios!$I$8:$I$67,Datos_escenarios!$B$8:$B$67,grupo_sim,Datos_escenarios!$C$8:$C$67,$B33) -> 0.6539123 | R33: =F33+B33/10000000 -> -10.216962 | S33: 19 | T33: =INDEX($C$15:$C$33,MATCH(SMALL($R$15:$R$33,S33),$R$15:$R$33,0)) -> Suba | U33: =INDEX($F$15:$F$33,MATCH(SMALL($R$15:$R$33,S33),$R$15:$R$33,0)) -> -5.0827249
B35: Es una sensibilidad del modelo, no un efecto causal.
B36: Escenario = (1 − f₁)(1 − f₂)·p00 + f₁(1 − f₂)·p10 + (1 − f₁)f₂·p01 + f₁f₂·p11, con f₁ = cobertura de alumbrado y f₂ = cobertura de parques sin atracos. p00 es la probabilidad media predicha hoy; p10, con el alumbrado resuelto para todos; p01, sin atracos en ningún parque; p11, con ambas palancas (hoja Datos_escenarios). Modelo: logit ponderado con perfil, delito registrado, hechos del entorno y alumbrado (Bienal 2025). Sirve para comparar territorios y priorizar; un piloto con línea base y grupo de comparación confirmaría el efecto.

Sheet Diccionario
B1: EL MIEDO QUE NO BAJA · BOGOTÁ DATAJAM 5 · THE DATA SQUAD | I1: ← Portada
B2: Diccionario
B3: Cada indicador y variable del libro: definición, unidad, fuente y año.
B6: Tipo | C6: Variable | D6: Nombre | E6: Definición | F6: Unidad | G6: Fuente | H6: Año / corte | I6: Dónde aparece
B7: Indicador | C7: poblacion | D7: Población | E7: Población total proyectada de la localidad (cabecera más rural). | F7: habitantes | G7: SDP, proyecciones de población 2005-2035 | H7: 2025 | I7: Panel_localidad
B8: Indicador | C8: zona_insegura | D8: Zona insegura | E8: Adultos que califican su zona como insegura o muy insegura (P66.8). Promedio ponderado con el factor de expansión. Resultado del modelo principal. | F8: % de adultos | G8: Encuesta Bienal de Cultura Ciudadana (SCRD) | H8: 2025 | I8: Panel_localidad, Indice_brecha, Modelos, Simulador
B9: Indicador | C9: ciudad_insegura | D9: Ciudad insegura | E9: Adultos que califican Bogotá como insegura o muy insegura (P74). | F9: % de adultos | G9: Encuesta Bienal de Cultura Ciudadana (SCRD) | H9: 2025 | I9: Panel_localidad, Resumen, Modelos
B10: Indicador | C10: ciudad_peor_que_antes | D10: Ciudad peor que antes | E10: Adultos que consideran que la seguridad de la ciudad está peor que antes (P77). | F10: % de adultos | G10: Encuesta Bienal de Cultura Ciudadana (SCRD) | H10: 2025 | I10: Panel_localidad
B11: Indicador | C11: miedo_espacio_publico | D11: Miedo en el espacio público | E11: Adultos que reportan miedo en el espacio público (P63). | F11: % de adultos | G11: Encuesta Bienal de Cultura Ciudadana (SCRD) | H11: 2025 | I11: Panel_localidad, Genero, Modelos
B12: Indicador | C12: alumbrado_malo | D12: Alumbrado público malo en su zona | E12: Califica como malo o muy malo el alumbrado público de su zona (P66.1). Palanca 1 del simulador. | F12: % en el panel; 0/1 en los modelos | G12: Encuesta Bienal de Cultura Ciudadana (SCRD) | H12: 2025 | I12: Panel_localidad, Modelos, Simulador
B13: Indicador | C13: parque_spa | D13: Venta o consumo de drogas en el parque | E13: Reporta venta o consumo de drogas en el parque más cercano (P72.10 o P72.11). | F13: % en el panel; 0/1 en los modelos | G13: Encuesta Bienal de Cultura Ciudadana (SCRD) | H13: 2025 | I13: Panel_localidad, Modelos
B14: Indicador | C14: parque_acoso | D14: Acoso en el parque | E14: Reporta acoso en el parque más cercano (P72.12). | F14: % de adultos | G14: Encuesta Bienal de Cultura Ciudadana (SCRD) | H14: 2025 | I14: Panel_localidad
B15: Indicador | C15: presencio_acoso | D15: Presenció acoso a mujeres | E15: Presenció acoso a mujeres (P11.1 o P11.4). | F15: % en el panel; 0/1 en los modelos | G15: Encuesta Bienal de Cultura Ciudadana (SCRD) | H15: 2025 | I15: Panel_localidad, Modelos
B16: Indicador | C16: emv_victima | D16: Víctima de un delito | E16: Adultos que fueron víctimas de un delito en el último año (Q144). En los modelos de la EMV es la variable de control «victima». | F16: % en el panel; 0/1 en los modelos | G16: Encuesta Mundial de Valores ola 8 (Datos para la Transparencia) | H16: 2024 | I16: Panel_localidad, Cifra_oculta, Genero
B17: Indicador | C17: emv_barrio_inseguro | D17: Barrio inseguro (EMV) | E17: Adultos que se sienten poco o nada seguros en su barrio (Q131, opciones 3 y 4). | F17: % en el panel; 0/1 en los modelos | G17: Encuesta Mundial de Valores ola 8 (Datos para la Transparencia) | H17: 2024 | I17: Panel_localidad, Genero
... B50: Medida derivada | C50: p00, p10, p01, p11 | D50: Escenarios del simulador | E50: Probabilidad media predicha de sentir insegura la zona hoy (p00), con alumbrado resuelto (p10), sin atracos en parques (p01) y con ambas (p11). | F50: % de adultos | G50: Cálculo propio | H50: 2025 | I50: Simulador, Datos_escenarios

Sheet Fuentes
B1: EL MIEDO QUE NO BAJA · BOGOTÁ DATAJAM 5 · THE DATA SQUAD | G1: ← Portada
B2: Fuentes
B3: Conjuntos de datos oficiales usados. Cada uno se descarga desde su servicio con caché local y registro de URL, fecha y sha1 (src/fuentes.py).
B6: Entidad | C6: Conjunto de datos | D6: Uso en el proyecto | E6: Portal (enlace) | F6: Descarga directa | G6: Archivo local (data/crudos/)
B7: Secretaría Distrital de Seguridad, Convivencia y Justicia (SCJ) | C7: Delito de Alto Impacto. Bogotá D.C. | D7: 11 delitos por localidad, enero-agosto 2018-2026 | E7: https://datosabiertos.bogota.gov.co/dataset/delito-de-alto-impacto-bogota-d-c | F7: Abrir | G7: scj_delitos_alto_impacto_localidad.csv
B8: SCJ (Línea 123, NUSE) | C8: Incidentes Reportados por localidad | D8: Llamadas 123 por narcóticos, riñas y maltrato a mujer, por localidad | E8: https://oaiee.scj.gov.co/agc/rest/services/Tematicos_Pub/CifrasSCJ/MapServer/2 | F8: Abrir | G8: scj_incidentes_123_localidad.csv
B9: SCJ (Línea 123, NUSE) | C9: Incidentes Reportados por UPZ | D9: Llamadas 123 por UPZ (mapas del visor) | E9: https://oaiee.scj.gov.co/agc/rest/services/Tematicos_Pub/CifrasSCJ/MapServer/3 | F9: Abrir | G9: scj_incidentes_123_upz.geojson
B10: Secretaría de Cultura, Recreación y Deporte · Observatorio de Culturas | C10: Encuesta Bienal de Cultura Ciudadana 2025 (módulo cultura ciudadana) | D10: Microdatos: percepción y entorno (5.538 adultos) | E10: https://observatoriocultura.github.io/observatorio/#/ebc/encuesta-cultura-ciudadana-2025 | F10: Abrir | G10: ebcc_2025_cultura_ciudadana.xlsx
B11: Alcaldía de Bogotá · Datos para la Transparencia (EMV Colombia, ola 8) | C11: Encuesta Mundial de Valores ola 8, 2024 | D11: Microdatos: victimización y género (1.824 encuestas en Bogotá) | E11: https://gobiernoabiertobogota.gov.co/transparencia | F11: Abrir | G11: emv_ola8_2024.xlsx
B12: Secretaría Distrital de Planeación (SDP) | C12: Proyecciones y retroproyecciones de población por localidad 2005-2035 | D12: Denominadores por localidad, sexo y edad | E12: https://datosabiertos.bogota.gov.co/dataset/proyecciones-y-retroproyecciones-de-poblacion-2005-2035 | F12: Abrir | G12: sdp_poblacion_localidad_2005_2035.ods
B13: Secretaría Distrital de Planeación (SDP) | C13: Proyecciones y retroproyecciones de población por UPZ 2005-2035 | D13: Denominadores por UPZ | E13: https://datosabiertos.bogota.gov.co/dataset/proyecciones-y-retroproyecciones-de-poblacion-2005-2035 | F13: Abrir | G13: sdp_poblacion_upz_2005_2035.ods
B14: UAECD · IDECA | C14: Localidad. Bogotá D.C. | D14: Límites y área de las localidades | E14: https://datosabiertos.bogota.gov.co/dataset/localidad-bogota-d-c | F14: Abrir | G14: ideca_localidades.geojson
B15: Unidad Administrativa Especial de Servicios Públicos (UAESP) | C15: Alumbrado público: luminarias por localidad y tecnología (corte agosto 2019, el último publicado) | D15: Validación del alumbrado (último corte: agosto de 2019) | E15: https://datosabiertos.bogota.gov.co/dataset/alumbrado_publico_lt | F15: Abrir | G15: uaesp_alumbrado_2019_08.csv
B16: Departamento Administrativo de la Defensoría del Espacio Público (DADEP) | C16: Indicador de espacio público efectivo por localidad | D16: Contexto: espacio público efectivo | E16: https://datosabiertos.bogota.gov.co/dataset/indicador-espacio-publico-localidad-bogota-d-c | F16: Abrir | G16: dadep_ep_efectivo_localidad.csv
B18: La localidad de cada encuesta de la EMV no viene en el archivo publicado: se recuperó del tablero oficial de Datos para la Transparencia (data/crudos/emv_localidad_por_registro.csv) y se verificó con la ficha técnica (96 encuestas por localidad). Los datos son de las entidades citadas y se usan bajo sus condiciones de datos abiertos.

Sheet Bitacora
B1: EL MIEDO QUE NO BAJA · BOGOTÁ DATAJAM 5 · THE DATA SQUAD | E1: ← Portada
B2: Bitácora de limpieza
B3: Cada paso de lectura, formato, llave territorial, recodificación e integración, tal como lo registró el pipeline (src/limpieza.py).
B6: N.º | C6: Fuente | D6: Paso | E6: Detalle
B7: 1 | C7: SCJ delitos | D7: lectura | E7: 21 filas (localidades + totales); corte 'Ene-Ago (2025vs2026)' para todos los años
B8: 2 | C8: SCJ delitos | D8: formato | E8: 117 columnas año×tipo pasadas a formato largo; 399 celdas vacías descartadas
B9: 3 | C9: SCJ delitos | D9: llave | E9: códigos de localidad 01-20 normalizados a entero; descartados no territoriales: [99]
B10: 4 | C10: SCJ delitos | D10: cobertura | E10: tipos sin dato 2026: ['LP']
B11: 5 | C11: SCJ incidentes 123 | D11: lectura | E11: 21 filas; corte 'Ene-Ago (2025vs2026)'
B12: 6 | C12: SCJ incidentes 123 | D12: formato | E12: 81 columnas año×tipo pasadas a formato largo; 0 celdas vacías descartadas
B13: 7 | C13: SDP población | D13: lectura | E13: 837 filas (unidad × año × área); 202 columnas sexo×edad simple
B14: 8 | C14: SDP población | D14: control | E14: Bogotá 2025 = 7,937,898 habitantes (suma de localidades, cabecera + rural)
B15: 9 | C15: SDP población UPZ | D15: lectura | E15: 3472 filas (unidad × año × área); 36 columnas sexo×edad simple
B16: 10 | C16: Bienal 2025 | D16: lectura | E16: hoja 'datos': 5860 personas × 537 variables
B17: 11 | C17: Bienal 2025 | D17: universo | E17: se conservan adultos (18+): 5639 de 5860; el modelo usa las 19 localidades urbanas
B18: 12 | C18: Bienal 2025 | D18: recodificación | E18: escalas 1-4/1-5 → 1 si 'malo/muy malo' o 'insegura/muy insegura'; 'no sabe' queda vacío
... B26: 20 | C26: Integración | D26: UPZ | E26: incidentes 123 por UPZ con población SDP; 3 UPZ sin población (rurales o nuevas) excluidas
B28: Fuente: outputs/tablas/bitacora_limpieza.csv.

Sheet Datos_escenarios
B1: EL MIEDO QUE NO BAJA · BOGOTÁ DATAJAM 5 · THE DATA SQUAD | I1: ← Portada
B2: Datos del simulador
B3: Probabilidad media predicha de sentir insegura la zona (logit ponderado, Bienal 2025), por grupo y localidad. Código 0 = Bogotá. Alimenta la hoja Simulador.
B7: Grupo | C7: Código | D7: Localidad | E7: Hoy (p00) | F7: Alumbrado resuelto (p10) | G7: Parques sin atracos (p01) | H7: Ambas palancas (p11) | I7: Observado (Bienal 2025)
B8: Total | C8: 0 | D8: Bogotá | E8: 0.48389448 | F8: 0.3745509 | G8: 0.44614907 | H8: 0.33486946 | I8: 0.48389448
B9: Total | C9: 1 | D9: Usaquén | E9: 0.32590431 | F9: 0.20569475 | G9: 0.30812428 | H9: 0.18998909 | I9: 0.24820972
B10: Total | C10: 2 | D10: Chapinero | E10: 0.40470974 | F10: 0.31300832 | G10: 0.35362936 | H10: 0.26305277 | I10: 0.50505065
B11: Total | C11: 3 | D11: Santa Fe | E11: 0.64535982 | F11: 0.4969368 | G11: 0.61400213 | H11: 0.45790341 | I11: 0.58063905
B12: Total | C12: 4 | D12: San Cristóbal | E12: 0.51234963 | F12: 0.41518493 | G12: 0.46795236 | H12: 0.36512826 | I12: 0.55734341
B13: Total | C13: 5 | D13: Usme | E13: 0.5686295 | F13: 0.42506058 | G13: 0.53227928 | H13: 0.38211801 | I13: 0.64641785
B14: Total | C14: 6 | D14: Tunjuelito | E14: 0.50741372 | F14: 0.32027383 | G14: 0.48077375 | H14: 0.29416079 | I14: 0.3598543
B15: Total | C15: 7 | D15: Bosa | E15: 0.55975086 | F15: 0.42911116 | G15: 0.51558236 | H15: 0.38287672 | I15: 0.57061377
B16: Total | C16: 8 | D16: Kennedy | E16: 0.49095758 | F16: 0.35828802 | G16: 0.46203667 | H16: 0.32894406 | I16: 0.58445401
B17: Total | C17: 9 | D17: Fontibón | E17: 0.38406274 | F17: 0.27810285 | G17: 0.35863427 | H17: 0.2537166 | I17: 0.27087933
B18: Total | C18: 10 | D18: Engativá | E18: 0.47317427 | F18: 0.37834151 | G18: 0.41927003 | H18: 0.32292367 | I18: 0.4939223
B19: Total | C19: 11 | D19: Suba | E19: 0.45139816 | F19: 0.3926506 | G19: 0.40865925 | H19: 0.34957564 | I19: 0.40472664
... B67: Hombres | C67: 19 | D67: Ciudad Bolívar | E67: 0.66655924 | F67: 0.51010939 | G67: 0.62405885 | H67: 0.45719157 | I67: 0.68697766
B69: Fuente: outputs/tablas/escenarios.csv (modelo con perfil, delito registrado, hechos del entorno y alumbrado malo). p10 = alumbrado deja de ser malo para todos; p01 = nadie ve atracos en su parque; p11 = ambas. Valores fijos: no editar.
